{"type": "FeatureCollection", "features": [{"type": "Feature", "geometry": {"type": "Point", "coordinates": [2.407424, 48.849236]}, "properties": {"numparc": 625, "etat de la localisation": "autre", "ID BDGEO": "27", "horodatage": "2021-06-02 10:13:53", "distance (en metres)": 1340.02, "station": "RUE DE LA GARE DE REUILLY", "marker-color": "#818181"}}, {"type": "Feature", "geometry": {"type": "Point", "coordinates": [2.397881, 48.848373]}, "properties": {"numparc": 625, "etat de la localisation": "autre", "ID BDGEO": "26", "horodatage": "2021-06-02 10:17:42", "distance (en metres)": 725.41, "station": "MONTGALLET", "marker-color": "#818181"}}, {"type": "Feature", "geometry": {"type": "Point", "coordinates": [2.39499, 48.848671]}, "properties": {"numparc": 625, "etat de la localisation": "autre", "ID BDGEO": "26", "horodatage": "2021-06-02 10:20:55", "distance (en metres)": 591.45, "station": "MONTGALLET", "marker-color": "#818181"}}, {"type": "Feature", "geometry": {"type": "Point", "coordinates": [2.39499, 48.848671]}, "properties": {"numparc": 625, "etat de la localisation": "autre", "ID BDGEO": "26", "horodatage": "2021-06-02 10:21:07", "distance (en metres)": 591.45, "station": "MONTGALLET", "marker-color": "#818181"}}, {"type": "Feature", "geometry": {"type": "Point", "coordinates": [2.39725, 48.848492]}, "properties": {"numparc": 625, "etat de la localisation": "autre", "ID BDGEO": "26", "horodatage": "2021-06-02 10:32:52", "distance (en metres)": 696.46, "station": "MONTGALLET", "marker-color": "#818181"}}, {"type": "Feature", "geometry": {"type": "Point", "coordinates": [2.406569, 48.847977]}, "properties": {"numparc": 625, "etat de la localisation": "autre", "ID BDGEO": "109", "horodatage": "2021-06-02 10:41:13", "distance (en metres)": 217.01, "station": "LAGNY SORTIE", "marker-color": "#818181"}}, {"type": "Feature", "geometry": {"type": "Point", "coordinates": [2.406569, 48.847977]}, "properties": {"numparc": 625, "etat de la localisation": "autre", "ID BDGEO": "109", "horodatage": "2021-06-02 10:43:21", "distance (en metres)": 217.01, "station": "LAGNY SORTIE", "marker-color": "#818181"}}, {"type": "Feature", "geometry": {"type": "Point", "coordinates": [2.407456, 48.848915]}, "properties": {"numparc": 625, "etat de la localisation": "autre", "ID BDGEO": "109", "horodatage": "2021-06-02 10:45:09", "distance (en metres)": 121.32, "station": "LAGNY SORTIE", "marker-color": "#818181"}}, {"type": "Feature", "geometry": {"type": "Point", "coordinates": [2.407456, 48.848915]}, "properties": {"numparc": 625, "etat de la localisation": "autre", "ID BDGEO": "109", "horodatage": "2021-06-02 10:45:15", "distance (en metres)": 121.32, "station": "LAGNY SORTIE", "marker-color": "#818181"}}, {"type": "Feature", "geometry": {"type": "Point", "coordinates": [2.407641, 48.849064]}, "properties": {"numparc": 625, "etat de la localisation": "autre", "ID BDGEO": "109", "horodatage": "2021-06-02 10:45:55", "distance (en metres)": 112.84, "station": "LAGNY SORTIE", "marker-color": "#818181"}}, {"type": "Feature", "geometry": {"type": "Point", "coordinates": [2.407641, 48.849064]}, "properties": {"numparc": 625, "etat de la localisation": "autre", "ID BDGEO": "109", "horodatage": "2021-06-02 10:47:38", "distance (en metres)": 112.84, "station": "LAGNY SORTIE", "marker-color": "#818181"}}, {"type": "Feature", "geometry": {"type": "Point", "coordinates": [2.407282, 48.84935]}, "properties": {"numparc": 625, "etat de la localisation": "autre", "ID BDGEO": "109", "horodatage": "2021-06-02 14:11:24", "distance (en metres)": 72.11, "station": "LAGNY SORTIE", "marker-color": "#818181"}}, {"type": "Feature", "geometry": {"type": "Point", "coordinates": [2.406816, 48.850216]}, "properties": {"numparc": 648, "etat de la localisation": "autre", "ID BDGEO": "110", "horodatage": "2021-06-03 02:12:33", "distance (en metres)": 63.57, "station": "LAGNY ENTREE", "marker-color": "#818181"}}, {"type": "Feature", "geometry": {"type": "Point", "coordinates": [2.393911, 48.841103]}, "properties": {"station": "RUE DE LA GARE DE REUILLY", "ID BDGEO": "27", "marker-color": "#56B3FF"}}, {"type": "Feature", "geometry": {"type": "Point", "coordinates": [2.389802, 48.844592]}, "properties": {"station": "MONTGALLET", "ID BDGEO": "26", "marker-color": "#56B3FF"}}, {"type": "Feature", "geometry": {"type": "Point", "coordinates": [2.406817, 48.849922]}, "properties": {"station": "LAGNY SORTIE", "ID BDGEO": "109", "marker-color": "#56B3FF"}}, {"type": "Feature", "geometry": {"type": "Point", "coordinates": [2.407321, 48.849751]}, "properties": {"station": "LAGNY ENTREE", "ID BDGEO": "110", "marker-color": "#56B3FF"}}]}