{"type": "FeatureCollection", "features": [{"type": "Feature", "geometry": {"type": "Point", "coordinates": [2.416856, 48.864689]}, "properties": {"numparc": 4946, "etat de la localisation": "autre", "ID BDGEO": "226", "horodatage": "2021-04-19 20:49:58", "distance (en metres)": 1748.3, "station": "CENTRE BUS LES LILAS-ENTREE", "marker-color": "#818181"}}, {"type": "Feature", "geometry": {"type": "Point", "coordinates": [2.416856, 48.864689]}, "properties": {"numparc": 4946, "etat de la localisation": "autre", "ID BDGEO": "226", "horodatage": "2021-04-19 20:54:16", "distance (en metres)": 1748.3, "station": "CENTRE BUS LES LILAS-ENTREE", "marker-color": "#818181"}}, {"type": "Feature", "geometry": {"type": "Point", "coordinates": [2.427363, 48.878811]}, "properties": {"station": "CENTRE BUS LES LILAS-ENTREE", "ID BDGEO": "226", "marker-color": "#56B3FF"}}]}