{"type": "FeatureCollection", "features": [{"type": "Feature", "geometry": {"type": "Point", "coordinates": [2.330105, 48.822708]}, "properties": {"numparc": 1392, "etat de la localisation": "autre", "ID BDGEO": "61", "horodatage": "2021-05-23 07:35:14", "distance (en metres)": 96.38, "station": "CENTRE BUS MONTROUGE SORTIE", "marker-color": "#818181"}}, {"type": "Feature", "geometry": {"type": "Point", "coordinates": [2.328789, 48.822709]}, "properties": {"station": "CENTRE BUS MONTROUGE SORTIE", "ID BDGEO": "61", "marker-color": "#56B3FF"}}]}