{"type": "FeatureCollection", "features": [{"type": "Feature", "geometry": {"type": "Point", "coordinates": [2.297934, 48.722408]}, "properties": {"numparc": 4882, "etat de la localisation": "autre", "ID BDGEO": "118", "horodatage": "2021-04-19 05:22:50", "distance (en metres)": 60.92, "station": "CENTRE BUS DE MASSY-SORTIE", "marker-color": "#818181"}}, {"type": "Feature", "geometry": {"type": "Point", "coordinates": [2.301499, 48.755619]}, "properties": {"numparc": 4882, "etat de la localisation": "autre", "ID BDGEO": "82", "horodatage": "2021-04-19 06:56:37", "distance (en metres)": 53.65, "station": "ANTONY RER", "marker-color": "#818181"}}, {"type": "Feature", "geometry": {"type": "Point", "coordinates": [2.298092, 48.721718]}, "properties": {"numparc": 4870, "etat de la localisation": "autre", "ID BDGEO": "118", "horodatage": "2021-04-19 11:31:14", "distance (en metres)": 75.13, "station": "CENTRE BUS DE MASSY-SORTIE", "marker-color": "#818181"}}, {"type": "Feature", "geometry": {"type": "Point", "coordinates": [2.297247, 48.7221]}, "properties": {"station": "CENTRE BUS DE MASSY-SORTIE", "ID BDGEO": "118", "marker-color": "#56B3FF"}}, {"type": "Feature", "geometry": {"type": "Point", "coordinates": [2.301273, 48.75516]}, "properties": {"station": "ANTONY RER", "ID BDGEO": "82", "marker-color": "#56B3FF"}}]}