{"type": "FeatureCollection", "features": [{"type": "Feature", "geometry": {"type": "Point", "coordinates": [2.44226, 48.77232]}, "properties": {"numparc": 2794, "etat de la localisation": "autre", "ID BDGEO": "3300", "horodatage": "2021-05-08 06:01:13", "distance (en metres)": 21529.57, "station": "DROITS DE L'HOMME#", "marker-color": "#818181"}}, {"type": "Feature", "geometry": {"type": "Point", "coordinates": [2.215576, 48.895706]}, "properties": {"station": "DROITS DE L'HOMME#", "ID BDGEO": "3300", "marker-color": "#56B3FF"}}]}