{"type": "FeatureCollection", "features": [{"type": "Feature", "geometry": {"type": "Point", "coordinates": [2.442992, 48.772762]}, "properties": {"numparc": 2786, "etat de la localisation": "autre", "ID BDGEO": "107", "horodatage": "2021-05-11 07:11:49", "distance (en metres)": 42.18, "station": "CENTRE BUS CRETEIL D", "marker-color": "#818181"}}, {"type": "Feature", "geometry": {"type": "Point", "coordinates": [2.442992, 48.772762]}, "properties": {"numparc": 2786, "etat de la localisation": "autre", "ID BDGEO": "107", "horodatage": "2021-05-11 07:17:54", "distance (en metres)": 42.18, "station": "CENTRE BUS CRETEIL D", "marker-color": "#818181"}}, {"type": "Feature", "geometry": {"type": "Point", "coordinates": [2.443292, 48.772438]}, "properties": {"station": "CENTRE BUS CRETEIL D", "ID BDGEO": "107", "marker-color": "#56B3FF"}}]}