{"type": "FeatureCollection", "features": [{"type": "Feature", "geometry": {"type": "Point", "coordinates": [2.441544, 48.772827]}, "properties": {"numparc": 2820, "etat de la localisation": "autre", "ID BDGEO": "203", "horodatage": "2021-05-31 05:10:24", "distance (en metres)": 135.52, "station": "DEPOT CRETEIL-SORTIE", "marker-color": "#818181"}}, {"type": "Feature", "geometry": {"type": "Point", "coordinates": [2.443292, 48.772429]}, "properties": {"station": "DEPOT CRETEIL-SORTIE", "ID BDGEO": "203", "marker-color": "#56B3FF"}}]}