{"type": "FeatureCollection", "features": [{"type": "Feature", "geometry": {"type": "Point", "coordinates": [2.427307, 48.878796]}, "properties": {"numparc": 4949, "etat de la localisation": "autre", "ID BDGEO": "15", "horodatage": "2021-04-02 21:25:01", "distance (en metres)": 44.82, "station": "DEPOT DES LILAS SORTIE#", "marker-color": "#818181"}}, {"type": "Feature", "geometry": {"type": "Point", "coordinates": [2.426974, 48.878765]}, "properties": {"numparc": 4949, "etat de la localisation": "autre", "ID BDGEO": "15", "horodatage": "2021-04-02 21:31:39", "distance (en metres)": 43.32, "station": "DEPOT DES LILAS SORTIE#", "marker-color": "#818181"}}, {"type": "Feature", "geometry": {"type": "Point", "coordinates": [2.428121, 48.878956]}, "properties": {"numparc": 4949, "etat de la localisation": "autre", "ID BDGEO": "15", "horodatage": "2021-04-03 06:55:03", "distance (en metres)": 83.24, "station": "DEPOT DES LILAS SORTIE#", "marker-color": "#818181"}}, {"type": "Feature", "geometry": {"type": "Point", "coordinates": [2.427549, 48.879044]}, "properties": {"numparc": 4949, "etat de la localisation": "autre", "ID BDGEO": "15", "horodatage": "2021-04-03 06:56:34", "distance (en metres)": 40.34, "station": "DEPOT DES LILAS SORTIE#", "marker-color": "#818181"}}, {"type": "Feature", "geometry": {"type": "Point", "coordinates": [2.428263, 48.878899]}, "properties": {"numparc": 4935, "etat de la localisation": "autre", "ID BDGEO": "15", "horodatage": "2021-04-03 12:51:14", "distance (en metres)": 94.98, "station": "DEPOT DES LILAS SORTIE#", "marker-color": "#818181"}}, {"type": "Feature", "geometry": {"type": "Point", "coordinates": [2.427023, 48.879153]}, "properties": {"station": "DEPOT DES LILAS SORTIE#", "ID BDGEO": "15", "marker-color": "#56B3FF"}}]}