{"type": "FeatureCollection", "features": [{"type": "Feature", "geometry": {"type": "Point", "coordinates": [2.424873, 48.879406]}, "properties": {"numparc": 4937, "etat de la localisation": "autre", "ID BDGEO": "24", "horodatage": "2021-06-05 07:44:17", "distance (en metres)": 157.57, "station": "LILAS DEPART.", "marker-color": "#818181"}}, {"type": "Feature", "geometry": {"type": "Point", "coordinates": [2.427023, 48.879315]}, "properties": {"station": "LILAS DEPART.", "ID BDGEO": "24", "marker-color": "#56B3FF"}}]}