{"type": "FeatureCollection", "features": [{"type": "Feature", "geometry": {"type": "Point", "coordinates": [2.441398, 48.861942]}, "properties": {"numparc": 4946, "etat de la localisation": "autre", "ID BDGEO": "137", "horodatage": "2021-04-04 18:45:27", "distance (en metres)": 55.1, "station": "MAIRIE DE MONTREUIL-METRO", "marker-color": "#818181"}}, {"type": "Feature", "geometry": {"type": "Point", "coordinates": [2.417451, 48.865242]}, "properties": {"numparc": 4946, "etat de la localisation": "autre", "ID BDGEO": "51", "horodatage": "2021-04-04 20:21:45", "distance (en metres)": 49.96, "station": "GALLIENI-METRO", "marker-color": "#818181"}}, {"type": "Feature", "geometry": {"type": "Point", "coordinates": [2.399135, 48.865753]}, "properties": {"numparc": 4946, "etat de la localisation": "autre", "ID BDGEO": "413", "horodatage": "2021-04-04 20:31:24", "distance (en metres)": 83.14, "station": "GAMBETTA-JAPON", "marker-color": "#818181"}}, {"type": "Feature", "geometry": {"type": "Point", "coordinates": [2.399502, 48.865788]}, "properties": {"numparc": 4946, "etat de la localisation": "autre", "ID BDGEO": "413", "horodatage": "2021-04-04 20:31:57", "distance (en metres)": 72.3, "station": "GAMBETTA-JAPON", "marker-color": "#818181"}}, {"type": "Feature", "geometry": {"type": "Point", "coordinates": [2.4414, 48.861897]}, "properties": {"numparc": 4946, "etat de la localisation": "autre", "ID BDGEO": "137", "horodatage": "2021-04-04 21:09:12", "distance (en metres)": 60.06, "station": "MAIRIE DE MONTREUIL-METRO", "marker-color": "#818181"}}, {"type": "Feature", "geometry": {"type": "Point", "coordinates": [2.399302, 48.865658]}, "properties": {"numparc": 4946, "etat de la localisation": "autre", "ID BDGEO": "413", "horodatage": "2021-04-04 22:30:17", "distance (en metres)": 67.21, "station": "GAMBETTA-JAPON", "marker-color": "#818181"}}, {"type": "Feature", "geometry": {"type": "Point", "coordinates": [2.441417, 48.861862]}, "properties": {"numparc": 4946, "etat de la localisation": "autre", "ID BDGEO": "137", "horodatage": "2021-04-04 23:16:14", "distance (en metres)": 63.81, "station": "MAIRIE DE MONTREUIL-METRO", "marker-color": "#818181"}}, {"type": "Feature", "geometry": {"type": "Point", "coordinates": [2.417426, 48.8652]}, "properties": {"numparc": 4946, "etat de la localisation": "autre", "ID BDGEO": "51", "horodatage": "2021-04-05 00:28:37", "distance (en metres)": 44.98, "station": "GALLIENI-METRO", "marker-color": "#818181"}}, {"type": "Feature", "geometry": {"type": "Point", "coordinates": [2.441487, 48.862434]}, "properties": {"station": "MAIRIE DE MONTREUIL-METRO", "ID BDGEO": "137", "marker-color": "#56B3FF"}}, {"type": "Feature", "geometry": {"type": "Point", "coordinates": [2.417136, 48.864843]}, "properties": {"station": "GALLIENI-METRO", "ID BDGEO": "51", "marker-color": "#56B3FF"}}, {"type": "Feature", "geometry": {"type": "Point", "coordinates": [2.399877, 48.865186]}, "properties": {"station": "GAMBETTA-JAPON", "ID BDGEO": "413", "marker-color": "#56B3FF"}}]}