{"type": "FeatureCollection", "features": [{"type": "Feature", "geometry": {"type": "Point", "coordinates": [2.427868, 48.879536]}, "properties": {"numparc": 4941, "etat de la localisation": "autre", "ID BDGEO": "193", "horodatage": "2021-04-25 06:43:57", "distance (en metres)": 456.33, "station": "SABLONS", "marker-color": "#818181"}}, {"type": "Feature", "geometry": {"type": "Point", "coordinates": [2.42309, 48.882176]}, "properties": {"station": "SABLONS", "ID BDGEO": "193", "marker-color": "#56B3FF"}}]}