{"type": "FeatureCollection", "features": [{"type": "Feature", "geometry": {"type": "Point", "coordinates": [2.328739, 48.823776]}, "properties": {"numparc": 641, "etat de la localisation": "autre", "ID BDGEO": "5429", "horodatage": "2021-05-17 17:22:44", "distance (en metres)": 104.4, "station": "MONTROUGE SORTIE#", "marker-color": "#818181"}}, {"type": "Feature", "geometry": {"type": "Point", "coordinates": [2.328739, 48.823776]}, "properties": {"numparc": 641, "etat de la localisation": "autre", "ID BDGEO": "5429", "horodatage": "2021-05-17 17:23:09", "distance (en metres)": 104.4, "station": "MONTROUGE SORTIE#", "marker-color": "#818181"}}, {"type": "Feature", "geometry": {"type": "Point", "coordinates": [2.329986, 48.823321]}, "properties": {"station": "MONTROUGE SORTIE#", "ID BDGEO": "5429", "marker-color": "#56B3FF"}}]}