{"type": "FeatureCollection", "features": [{"type": "Feature", "geometry": {"type": "Point", "coordinates": [2.332722, 48.853222]}, "properties": {"numparc": 681, "etat de la localisation": "autre", "ID BDGEO": "2", "horodatage": "2021-04-20 13:30:44", "distance (en metres)": 130.98, "station": "SAINT-GERMAIN DES PRES", "marker-color": "#818181"}}, {"type": "Feature", "geometry": {"type": "Point", "coordinates": [2.366462, 48.852303]}, "properties": {"numparc": 681, "etat de la localisation": "autre", "ID BDGEO": "133", "horodatage": "2021-04-20 13:53:19", "distance (en metres)": 49.67, "station": "BASTILLE-HENRI IV", "marker-color": "#818181"}}, {"type": "Feature", "geometry": {"type": "Point", "coordinates": [2.371076, 48.852673]}, "properties": {"numparc": 681, "etat de la localisation": "autre", "ID BDGEO": "26", "horodatage": "2021-04-20 13:56:59", "distance (en metres)": 50.58, "station": "BASTILLE-FBG ST-ANTOINE", "marker-color": "#818181"}}, {"type": "Feature", "geometry": {"type": "Point", "coordinates": [2.417634, 48.84293]}, "properties": {"numparc": 681, "etat de la localisation": "autre", "ID BDGEO": "55", "horodatage": "2021-04-20 14:19:24", "distance (en metres)": 43.44, "station": "MAIRIE DE SAINT-MANDE", "marker-color": "#818181"}}, {"type": "Feature", "geometry": {"type": "Point", "coordinates": [2.371142, 48.852787]}, "properties": {"numparc": 681, "etat de la localisation": "autre", "ID BDGEO": "26", "horodatage": "2021-04-20 16:01:16", "distance (en metres)": 43.88, "station": "BASTILLE-FBG ST-ANTOINE", "marker-color": "#818181"}}, {"type": "Feature", "geometry": {"type": "Point", "coordinates": [2.366452, 48.852303]}, "properties": {"numparc": 681, "etat de la localisation": "autre", "ID BDGEO": "133", "horodatage": "2021-04-20 18:07:02", "distance (en metres)": 50.38, "station": "BASTILLE-HENRI IV", "marker-color": "#818181"}}, {"type": "Feature", "geometry": {"type": "Point", "coordinates": [2.37123, 48.852757]}, "properties": {"numparc": 681, "etat de la localisation": "autre", "ID BDGEO": "26", "horodatage": "2021-04-20 18:12:17", "distance (en metres)": 50.9, "station": "BASTILLE-FBG ST-ANTOINE", "marker-color": "#818181"}}, {"type": "Feature", "geometry": {"type": "Point", "coordinates": [2.417652, 48.842876]}, "properties": {"numparc": 681, "etat de la localisation": "autre", "ID BDGEO": "55", "horodatage": "2021-04-20 18:34:05", "distance (en metres)": 49.3, "station": "MAIRIE DE SAINT-MANDE", "marker-color": "#818181"}}, {"type": "Feature", "geometry": {"type": "Point", "coordinates": [2.366477, 48.852356]}, "properties": {"numparc": 681, "etat de la localisation": "autre", "ID BDGEO": "133", "horodatage": "2021-04-20 19:59:01", "distance (en metres)": 47.51, "station": "BASTILLE-HENRI IV", "marker-color": "#818181"}}, {"type": "Feature", "geometry": {"type": "Point", "coordinates": [2.407562, 48.849453]}, "properties": {"numparc": 681, "etat de la localisation": "autre", "ID BDGEO": "88", "horodatage": "2021-04-20 20:35:23", "distance (en metres)": 68.73, "station": "LAGNY SORTIE", "marker-color": "#818181"}}, {"type": "Feature", "geometry": {"type": "Point", "coordinates": [2.334476, 48.853456]}, "properties": {"station": "SAINT-GERMAIN DES PRES", "ID BDGEO": "2", "marker-color": "#56B3FF"}}, {"type": "Feature", "geometry": {"type": "Point", "coordinates": [2.367121, 48.85241]}, "properties": {"station": "BASTILLE-HENRI IV", "ID BDGEO": "133", "marker-color": "#56B3FF"}}, {"type": "Feature", "geometry": {"type": "Point", "coordinates": [2.370703, 48.853056]}, "properties": {"station": "BASTILLE-FBG ST-ANTOINE", "ID BDGEO": "26", "marker-color": "#56B3FF"}}, {"type": "Feature", "geometry": {"type": "Point", "coordinates": [2.417702, 48.843318]}, "properties": {"station": "MAIRIE DE SAINT-MANDE", "ID BDGEO": "55", "marker-color": "#56B3FF"}}, {"type": "Feature", "geometry": {"type": "Point", "coordinates": [2.406831, 48.849841]}, "properties": {"station": "LAGNY SORTIE", "ID BDGEO": "88", "marker-color": "#56B3FF"}}]}