{"type": "FeatureCollection", "features": [{"type": "Feature", "geometry": {"type": "Point", "coordinates": [2.426618, 48.878868]}, "properties": {"numparc": 4938, "etat de la localisation": "autre", "ID BDGEO": "24", "horodatage": "2021-04-28 08:55:57", "distance (en metres)": 57.87, "station": "LILAS DEPART.", "marker-color": "#818181"}}, {"type": "Feature", "geometry": {"type": "Point", "coordinates": [2.427352, 48.878693]}, "properties": {"numparc": 4946, "etat de la localisation": "autre", "ID BDGEO": "252", "horodatage": "2021-04-28 10:01:53", "distance (en metres)": 1617.28, "station": "TROIS COMMUNES", "marker-color": "#818181"}}, {"type": "Feature", "geometry": {"type": "Point", "coordinates": [2.427842, 48.879028]}, "properties": {"numparc": 4938, "etat de la localisation": "autre", "ID BDGEO": "24", "horodatage": "2021-04-28 10:07:49", "distance (en metres)": 67.85, "station": "LILAS DEPART.", "marker-color": "#818181"}}, {"type": "Feature", "geometry": {"type": "Point", "coordinates": [2.427654, 48.878792]}, "properties": {"numparc": 4946, "etat de la localisation": "autre", "ID BDGEO": "252", "horodatage": "2021-04-28 17:07:16", "distance (en metres)": 1595.46, "station": "TROIS COMMUNES", "marker-color": "#818181"}}, {"type": "Feature", "geometry": {"type": "Point", "coordinates": [2.427548, 48.878906]}, "properties": {"numparc": 4938, "etat de la localisation": "autre", "ID BDGEO": "24", "horodatage": "2021-04-29 00:45:33", "distance (en metres)": 59.51, "station": "LILAS DEPART.", "marker-color": "#818181"}}, {"type": "Feature", "geometry": {"type": "Point", "coordinates": [2.428674, 48.878891]}, "properties": {"numparc": 4946, "etat de la localisation": "autre", "ID BDGEO": "252", "horodatage": "2021-04-29 01:01:58", "distance (en metres)": 1521.25, "station": "TROIS COMMUNES", "marker-color": "#818181"}}, {"type": "Feature", "geometry": {"type": "Point", "coordinates": [2.428674, 48.878891]}, "properties": {"numparc": 4946, "etat de la localisation": "autre", "ID BDGEO": "252", "horodatage": "2021-04-29 01:27:58", "distance (en metres)": 1521.25, "station": "TROIS COMMUNES", "marker-color": "#818181"}}, {"type": "Feature", "geometry": {"type": "Point", "coordinates": [2.427023, 48.879315]}, "properties": {"station": "LILAS DEPART.", "ID BDGEO": "24", "marker-color": "#56B3FF"}}, {"type": "Feature", "geometry": {"type": "Point", "coordinates": [2.449463, 48.878406]}, "properties": {"station": "TROIS COMMUNES", "ID BDGEO": "252", "marker-color": "#56B3FF"}}]}