{"type": "FeatureCollection", "features": [{"type": "Feature", "geometry": {"type": "Point", "coordinates": [2.297118, 48.721218]}, "properties": {"numparc": 4843, "etat de la localisation": "autre", "ID BDGEO": "756", "horodatage": "2021-04-17 14:07:04", "distance (en metres)": 81.42, "station": "MASSY DEPART", "marker-color": "#818181"}}, {"type": "Feature", "geometry": {"type": "Point", "coordinates": [2.265723, 48.728577]}, "properties": {"numparc": 4843, "etat de la localisation": "autre", "ID BDGEO": "212", "horodatage": "2021-04-17 17:20:54", "distance (en metres)": 65.96, "station": "CHEMIN DES FEMMES", "marker-color": "#818181"}}, {"type": "Feature", "geometry": {"type": "Point", "coordinates": [2.295189, 48.717163]}, "properties": {"numparc": 4843, "etat de la localisation": "autre", "ID BDGEO": "246", "horodatage": "2021-04-17 19:16:15", "distance (en metres)": 71.75, "station": "RUE DES FLEURS", "marker-color": "#818181"}}, {"type": "Feature", "geometry": {"type": "Point", "coordinates": [2.260815, 48.725323]}, "properties": {"numparc": 4851, "etat de la localisation": "autre", "ID BDGEO": "206", "horodatage": "2021-04-17 19:40:15", "distance (en metres)": 40.38, "station": "MASSY-PALAISEAU RER", "marker-color": "#818181"}}, {"type": "Feature", "geometry": {"type": "Point", "coordinates": [2.273059, 48.727341]}, "properties": {"numparc": 4851, "etat de la localisation": "autre", "ID BDGEO": "238", "horodatage": "2021-04-17 19:45:22", "distance (en metres)": 120.11, "station": "8 MAI 1945", "marker-color": "#818181"}}, {"type": "Feature", "geometry": {"type": "Point", "coordinates": [2.260701, 48.725407]}, "properties": {"numparc": 4851, "etat de la localisation": "autre", "ID BDGEO": "206", "horodatage": "2021-04-17 21:20:09", "distance (en metres)": 42.14, "station": "MASSY-PALAISEAU RER", "marker-color": "#818181"}}, {"type": "Feature", "geometry": {"type": "Point", "coordinates": [2.259708, 48.724728]}, "properties": {"numparc": 4851, "etat de la localisation": "autre", "ID BDGEO": "206", "horodatage": "2021-04-17 23:14:59", "distance (en metres)": 64.4, "station": "MASSY-PALAISEAU RER", "marker-color": "#818181"}}, {"type": "Feature", "geometry": {"type": "Point", "coordinates": [2.29722, 48.721947]}, "properties": {"station": "MASSY DEPART", "ID BDGEO": "756", "marker-color": "#56B3FF"}}, {"type": "Feature", "geometry": {"type": "Point", "coordinates": [2.265192, 48.728098]}, "properties": {"station": "CHEMIN DES FEMMES", "ID BDGEO": "212", "marker-color": "#56B3FF"}}, {"type": "Feature", "geometry": {"type": "Point", "coordinates": [2.29573, 48.716626]}, "properties": {"station": "RUE DES FLEURS", "ID BDGEO": "246", "marker-color": "#56B3FF"}}, {"type": "Feature", "geometry": {"type": "Point", "coordinates": [2.260401, 48.725084]}, "properties": {"station": "MASSY-PALAISEAU RER", "ID BDGEO": "206", "marker-color": "#56B3FF"}}, {"type": "Feature", "geometry": {"type": "Point", "coordinates": [2.27469, 48.727438]}, "properties": {"station": "8 MAI 1945", "ID BDGEO": "238", "marker-color": "#56B3FF"}}]}