{"type": "FeatureCollection", "features": [{"type": "Feature", "geometry": {"type": "Point", "coordinates": [2.333066, 48.869061]}, "properties": {"numparc": 1392, "etat de la localisation": "autre", "ID BDGEO": "128", "horodatage": "2021-06-24 09:40:15", "distance (en metres)": 82.23, "station": "OPERA-4 SEPTEMBRE", "marker-color": "#818181"}}, {"type": "Feature", "geometry": {"type": "Point", "coordinates": [2.333021, 48.869171]}, "properties": {"numparc": 1392, "etat de la localisation": "autre", "ID BDGEO": "128", "horodatage": "2021-06-24 18:31:45", "distance (en metres)": 69.57, "station": "OPERA-4 SEPTEMBRE", "marker-color": "#818181"}}, {"type": "Feature", "geometry": {"type": "Point", "coordinates": [2.327959, 48.823761]}, "properties": {"numparc": 1392, "etat de la localisation": "autre", "ID BDGEO": "61", "horodatage": "2021-06-24 20:47:54", "distance (en metres)": 131.76, "station": "CENTRE BUS MONTROUGE SORTIE", "marker-color": "#818181"}}, {"type": "Feature", "geometry": {"type": "Point", "coordinates": [2.332786, 48.869777]}, "properties": {"station": "OPERA-4 SEPTEMBRE", "ID BDGEO": "128", "marker-color": "#56B3FF"}}, {"type": "Feature", "geometry": {"type": "Point", "coordinates": [2.328789, 48.822709]}, "properties": {"station": "CENTRE BUS MONTROUGE SORTIE", "ID BDGEO": "61", "marker-color": "#56B3FF"}}]}