{"type": "FeatureCollection", "features": [{"type": "Feature", "geometry": {"type": "Point", "coordinates": [2.36811, 48.911037]}, "properties": {"numparc": 5651, "etat de la localisation": "autre", "ID BDGEO": "753", "horodatage": "2021-06-04 05:48:02", "distance (en metres)": 152.58, "station": "ENTREE AUBERV", "marker-color": "#818181"}}, {"type": "Feature", "geometry": {"type": "Point", "coordinates": [2.36984, 48.910269]}, "properties": {"station": "ENTREE AUBERV", "ID BDGEO": "753", "marker-color": "#56B3FF"}}]}