{"type": "FeatureCollection", "features": [{"type": "Feature", "geometry": {"type": "Point", "coordinates": [2.329879, 48.822704]}, "properties": {"numparc": 1367, "etat de la localisation": "autre", "ID BDGEO": "5416", "horodatage": "2021-05-07 07:13:08", "distance (en metres)": 1916.6, "station": "PORTE DE VANVES", "marker-color": "#818181"}}, {"type": "Feature", "geometry": {"type": "Point", "coordinates": [2.304571, 48.827118]}, "properties": {"station": "PORTE DE VANVES", "ID BDGEO": "5416", "marker-color": "#56B3FF"}}]}