{"type": "FeatureCollection", "features": [{"type": "Feature", "geometry": {"type": "Point", "coordinates": [2.351132, 48.895931]}, "properties": {"numparc": 6897, "etat de la localisation": "autre", "ID BDGEO": "234", "horodatage": "2021-05-06 09:53:47", "distance (en metres)": 497.64, "station": "MARCADET-POISSONNIERS", "marker-color": "#818181"}}, {"type": "Feature", "geometry": {"type": "Point", "coordinates": [2.350189, 48.891499]}, "properties": {"station": "MARCADET-POISSONNIERS", "ID BDGEO": "234", "marker-color": "#56B3FF"}}]}