{"type": "FeatureCollection", "features": [{"type": "Feature", "geometry": {"type": "Point", "coordinates": [2.357707, 48.875648]}, "properties": {"numparc": 5684, "etat de la localisation": "autre", "ID BDGEO": "36", "horodatage": "2021-04-03 13:13:29", "distance (en metres)": 18960.61, "station": "SQUARE CONDORCET.", "marker-color": "#818181"}}, {"type": "Feature", "geometry": {"type": "Point", "coordinates": [2.296031, 48.875008]}, "properties": {"numparc": 5688, "etat de la localisation": "autre", "ID BDGEO": "36", "horodatage": "2021-04-03 16:40:28", "distance (en metres)": 18889.18, "station": "SQUARE CONDORCET.", "marker-color": "#818181"}}, {"type": "Feature", "geometry": {"type": "Point", "coordinates": [2.298991, 48.879017]}, "properties": {"numparc": 5688, "etat de la localisation": "autre", "ID BDGEO": "36", "horodatage": "2021-04-03 16:42:14", "distance (en metres)": 19307.73, "station": "SQUARE CONDORCET.", "marker-color": "#818181"}}, {"type": "Feature", "geometry": {"type": "Point", "coordinates": [2.326825, 48.70635]}, "properties": {"station": "SQUARE CONDORCET.", "ID BDGEO": "36", "marker-color": "#56B3FF"}}]}