{"type": "FeatureCollection", "features": [{"type": "Feature", "geometry": {"type": "Point", "coordinates": [2.348179, 48.8964]}, "properties": {"numparc": 4410, "etat de la localisation": "autre", "ID BDGEO": "450", "horodatage": "2021-06-04 06:53:00", "distance (en metres)": 107.57, "station": "SORTIE DEPOT", "marker-color": "#818181"}}, {"type": "Feature", "geometry": {"type": "Point", "coordinates": [2.345352, 48.892944]}, "properties": {"numparc": 4410, "etat de la localisation": "autre", "ID BDGEO": "130", "horodatage": "2021-06-04 07:08:51", "distance (en metres)": 2690.69, "station": "SAINT AUGUSTIN", "marker-color": "#818181"}}, {"type": "Feature", "geometry": {"type": "Point", "coordinates": [2.345557, 48.890484]}, "properties": {"numparc": 4410, "etat de la localisation": "autre", "ID BDGEO": "130", "horodatage": "2021-06-04 07:12:23", "distance (en metres)": 2499.44, "station": "SAINT AUGUSTIN", "marker-color": "#818181"}}, {"type": "Feature", "geometry": {"type": "Point", "coordinates": [2.346108, 48.888912]}, "properties": {"numparc": 4410, "etat de la localisation": "autre", "ID BDGEO": "130", "horodatage": "2021-06-04 07:14:21", "distance (en metres)": 2408.56, "station": "SAINT AUGUSTIN", "marker-color": "#818181"}}, {"type": "Feature", "geometry": {"type": "Point", "coordinates": [2.343366, 48.889687]}, "properties": {"numparc": 4410, "etat de la localisation": "autre", "ID BDGEO": "130", "horodatage": "2021-06-04 07:15:33", "distance (en metres)": 2324.25, "station": "SAINT AUGUSTIN", "marker-color": "#818181"}}, {"type": "Feature", "geometry": {"type": "Point", "coordinates": [2.323813, 48.875877]}, "properties": {"numparc": 4410, "etat de la localisation": "autre", "ID BDGEO": "119", "horodatage": "2021-06-04 07:27:38", "distance (en metres)": 94.26, "station": "GARE SAINT-LAZARE-ROME", "marker-color": "#818181"}}, {"type": "Feature", "geometry": {"type": "Point", "coordinates": [2.323813, 48.875877]}, "properties": {"numparc": 4410, "etat de la localisation": "autre", "ID BDGEO": "119", "horodatage": "2021-06-04 07:28:03", "distance (en metres)": 94.26, "station": "GARE SAINT-LAZARE-ROME", "marker-color": "#818181"}}, {"type": "Feature", "geometry": {"type": "Point", "coordinates": [2.344482, 48.892975]}, "properties": {"numparc": 4410, "etat de la localisation": "autre", "ID BDGEO": "4", "horodatage": "2021-06-04 09:26:04", "distance (en metres)": 55.88, "station": "MAIRIE DU 18E-J. JOFFRIN", "marker-color": "#818181"}}, {"type": "Feature", "geometry": {"type": "Point", "coordinates": [2.349004, 48.896412]}, "properties": {"numparc": 4391, "etat de la localisation": "autre", "ID BDGEO": "450", "horodatage": "2021-06-04 09:56:45", "distance (en metres)": 56.0, "station": "SORTIE DEPOT", "marker-color": "#818181"}}, {"type": "Feature", "geometry": {"type": "Point", "coordinates": [2.323693, 48.875862]}, "properties": {"numparc": 4410, "etat de la localisation": "autre", "ID BDGEO": "119", "horodatage": "2021-06-04 10:06:21", "distance (en metres)": 93.13, "station": "GARE SAINT-LAZARE-ROME", "marker-color": "#818181"}}, {"type": "Feature", "geometry": {"type": "Point", "coordinates": [2.344619, 48.892914]}, "properties": {"numparc": 4410, "etat de la localisation": "autre", "ID BDGEO": "4", "horodatage": "2021-06-04 11:55:52", "distance (en metres)": 45.53, "station": "MAIRIE DU 18E-J. JOFFRIN", "marker-color": "#818181"}}, {"type": "Feature", "geometry": {"type": "Point", "coordinates": [2.344619, 48.892914]}, "properties": {"numparc": 4410, "etat de la localisation": "autre", "ID BDGEO": "4", "horodatage": "2021-06-04 11:56:05", "distance (en metres)": 45.53, "station": "MAIRIE DU 18E-J. JOFFRIN", "marker-color": "#818181"}}, {"type": "Feature", "geometry": {"type": "Point", "coordinates": [2.323827, 48.875839]}, "properties": {"numparc": 4410, "etat de la localisation": "autre", "ID BDGEO": "119", "horodatage": "2021-06-04 12:38:38", "distance (en metres)": 98.58, "station": "GARE SAINT-LAZARE-ROME", "marker-color": "#818181"}}, {"type": "Feature", "geometry": {"type": "Point", "coordinates": [2.349536, 48.896774]}, "properties": {"station": "SORTIE DEPOT", "ID BDGEO": "450", "marker-color": "#56B3FF"}}, {"type": "Feature", "geometry": {"type": "Point", "coordinates": [2.321477, 48.874531]}, "properties": {"station": "SAINT AUGUSTIN", "ID BDGEO": "130", "marker-color": "#56B3FF"}}, {"type": "Feature", "geometry": {"type": "Point", "coordinates": [2.323357, 48.87667]}, "properties": {"station": "GARE SAINT-LAZARE-ROME", "ID BDGEO": "119", "marker-color": "#56B3FF"}}, {"type": "Feature", "geometry": {"type": "Point", "coordinates": [2.345242, 48.892919]}, "properties": {"station": "MAIRIE DU 18E-J. JOFFRIN", "ID BDGEO": "4", "marker-color": "#56B3FF"}}]}