{"type": "FeatureCollection", "features": [{"type": "Feature", "geometry": {"type": "Point", "coordinates": [2.44095, 48.882309]}, "properties": {"numparc": 4946, "etat de la localisation": "autre", "ID BDGEO": "21023", "horodatage": "2021-05-04 00:29:24", "distance (en metres)": 104.08, "station": "ROMAINVILLE-CARNOT", "marker-color": "#818181"}}, {"type": "Feature", "geometry": {"type": "Point", "coordinates": [2.22964, 48.829544]}, "properties": {"numparc": 4946, "etat de la localisation": "autre", "ID BDGEO": "22551", "horodatage": "2021-05-04 01:37:27", "distance (en metres)": 127.98, "station": "PONT DE SEVRES", "marker-color": "#818181"}}, {"type": "Feature", "geometry": {"type": "Point", "coordinates": [2.265731, 48.841007]}, "properties": {"numparc": 4946, "etat de la localisation": "autre", "ID BDGEO": "17268", "horodatage": "2021-05-04 01:54:42", "distance (en metres)": 62.59, "station": "VERSAILLES-EXELMANS", "marker-color": "#818181"}}, {"type": "Feature", "geometry": {"type": "Point", "coordinates": [2.274085, 48.847672]}, "properties": {"numparc": 4946, "etat de la localisation": "autre", "ID BDGEO": "17265", "horodatage": "2021-05-04 01:57:10", "distance (en metres)": 99.82, "station": "PONT MIRABEAU", "marker-color": "#818181"}}, {"type": "Feature", "geometry": {"type": "Point", "coordinates": [2.319717, 48.841843]}, "properties": {"numparc": 4946, "etat de la localisation": "autre", "ID BDGEO": "21015", "horodatage": "2021-05-04 02:09:06", "distance (en metres)": 43.28, "station": "GARE MONTPARNASSE", "marker-color": "#818181"}}, {"type": "Feature", "geometry": {"type": "Point", "coordinates": [2.319943, 48.842068]}, "properties": {"numparc": 4930, "etat de la localisation": "autre", "ID BDGEO": "17255", "horodatage": "2021-05-04 02:11:42", "distance (en metres)": 46.19, "station": "GARE MONTPARNASSE", "marker-color": "#818181"}}, {"type": "Feature", "geometry": {"type": "Point", "coordinates": [2.440807, 48.88324]}, "properties": {"station": "ROMAINVILLE-CARNOT", "ID BDGEO": "21023", "marker-color": "#56B3FF"}}, {"type": "Feature", "geometry": {"type": "Point", "coordinates": [2.231345, 48.829799]}, "properties": {"station": "PONT DE SEVRES", "ID BDGEO": "22551", "marker-color": "#56B3FF"}}, {"type": "Feature", "geometry": {"type": "Point", "coordinates": [2.266328, 48.84141]}, "properties": {"station": "VERSAILLES-EXELMANS", "ID BDGEO": "17268", "marker-color": "#56B3FF"}}, {"type": "Feature", "geometry": {"type": "Point", "coordinates": [2.273238, 48.846968]}, "properties": {"station": "PONT MIRABEAU", "ID BDGEO": "17265", "marker-color": "#56B3FF"}}, {"type": "Feature", "geometry": {"type": "Point", "coordinates": [2.320289, 48.841942]}, "properties": {"station": "GARE MONTPARNASSE", "ID BDGEO": "21015", "marker-color": "#56B3FF"}}, {"type": "Feature", "geometry": {"type": "Point", "coordinates": [2.319404, 48.841852]}, "properties": {"station": "GARE MONTPARNASSE", "ID BDGEO": "17255", "marker-color": "#56B3FF"}}]}