{"type": "FeatureCollection", "features": [{"type": "Feature", "geometry": {"type": "Point", "coordinates": [2.406502, 48.876808]}, "properties": {"numparc": 4932, "etat de la localisation": "autre", "ID BDGEO": "152", "horodatage": "2021-04-02 21:10:35", "distance (en metres)": 107.79, "station": "PORTE DES LILAS-METRO.", "marker-color": "#818181"}}, {"type": "Feature", "geometry": {"type": "Point", "coordinates": [2.427261, 48.878811]}, "properties": {"numparc": 4932, "etat de la localisation": "autre", "ID BDGEO": "152", "horodatage": "2021-04-02 21:21:33", "distance (en metres)": 1590.44, "station": "PORTE DES LILAS-METRO.", "marker-color": "#818181"}}, {"type": "Feature", "geometry": {"type": "Point", "coordinates": [2.428532, 48.87888]}, "properties": {"numparc": 4932, "etat de la localisation": "autre", "ID BDGEO": "152", "horodatage": "2021-04-02 21:28:37", "distance (en metres)": 1683.05, "station": "PORTE DES LILAS-METRO.", "marker-color": "#818181"}}, {"type": "Feature", "geometry": {"type": "Point", "coordinates": [2.430468, 48.878891]}, "properties": {"numparc": 4932, "etat de la localisation": "autre", "ID BDGEO": "152", "horodatage": "2021-04-03 06:58:20", "distance (en metres)": 1822.3, "station": "PORTE DES LILAS-METRO.", "marker-color": "#818181"}}, {"type": "Feature", "geometry": {"type": "Point", "coordinates": [2.405966, 48.875905]}, "properties": {"station": "PORTE DES LILAS-METRO.", "ID BDGEO": "152", "marker-color": "#56B3FF"}}]}