{"type": "FeatureCollection", "features": [{"type": "Feature", "geometry": {"type": "Point", "coordinates": [2.613957, 48.850819]}, "properties": {"numparc": 4967, "etat de la localisation": "autre", "ID BDGEO": "82", "horodatage": "2021-06-23 23:27:45", "distance (en metres)": 3235.62, "station": "TORCY-RER#", "marker-color": "#818181"}}, {"type": "Feature", "geometry": {"type": "Point", "coordinates": [2.601641, 48.852375]}, "properties": {"numparc": 4967, "etat de la localisation": "autre", "ID BDGEO": "82", "horodatage": "2021-06-23 23:30:23", "distance (en metres)": 4134.5, "station": "TORCY-RER#", "marker-color": "#818181"}}, {"type": "Feature", "geometry": {"type": "Point", "coordinates": [2.654346, 48.838978]}, "properties": {"station": "TORCY-RER#", "ID BDGEO": "82", "marker-color": "#56B3FF"}}]}