{"type": "FeatureCollection", "features": [{"type": "Feature", "geometry": {"type": "Point", "coordinates": [2.244895, 48.729282]}, "properties": {"numparc": 5815, "etat de la localisation": "autre", "ID BDGEO": "96", "horodatage": "2021-06-19 20:33:16", "distance (en metres)": 82.56, "station": "CENTRE COMMERCIAL", "marker-color": "#818181"}}, {"type": "Feature", "geometry": {"type": "Point", "coordinates": [2.298639, 48.722427]}, "properties": {"numparc": 5815, "etat de la localisation": "autre", "ID BDGEO": "54", "horodatage": "2021-06-19 20:56:50", "distance (en metres)": 122.49, "station": "CENTRE BUS DE MASSY-SORTIE", "marker-color": "#818181"}}, {"type": "Feature", "geometry": {"type": "Point", "coordinates": [2.245097, 48.728552]}, "properties": {"station": "CENTRE COMMERCIAL", "ID BDGEO": "96", "marker-color": "#56B3FF"}}, {"type": "Feature", "geometry": {"type": "Point", "coordinates": [2.297859, 48.721453]}, "properties": {"station": "CENTRE BUS DE MASSY-SORTIE", "ID BDGEO": "54", "marker-color": "#56B3FF"}}]}