{"type": "FeatureCollection", "features": [{"type": "Feature", "geometry": {"type": "Point", "coordinates": [2.329407, 48.822746]}, "properties": {"numparc": 1411, "etat de la localisation": "autre", "ID BDGEO": "2", "horodatage": "2021-04-05 07:40:05", "distance (en metres)": 315.54, "station": "PORTE D'ORLEANS.", "marker-color": "#818181"}}, {"type": "Feature", "geometry": {"type": "Point", "coordinates": [2.317314, 48.797424]}, "properties": {"numparc": 1411, "etat de la localisation": "autre", "ID BDGEO": "114", "horodatage": "2021-04-05 07:58:41", "distance (en metres)": 100.79, "station": "PASTEUR-MEUNIERS", "marker-color": "#818181"}}, {"type": "Feature", "geometry": {"type": "Point", "coordinates": [2.302719, 48.78598]}, "properties": {"numparc": 1411, "etat de la localisation": "autre", "ID BDGEO": "90", "horodatage": "2021-04-05 08:27:29", "distance (en metres)": 136.21, "station": "LES BLAGIS", "marker-color": "#818181"}}, {"type": "Feature", "geometry": {"type": "Point", "coordinates": [2.325556, 48.821377]}, "properties": {"numparc": 1411, "etat de la localisation": "autre", "ID BDGEO": "223", "horodatage": "2021-04-05 08:39:54", "distance (en metres)": 76.77, "station": "PORTE D'ORLEANS", "marker-color": "#818181"}}, {"type": "Feature", "geometry": {"type": "Point", "coordinates": [2.317295, 48.797421]}, "properties": {"numparc": 1411, "etat de la localisation": "autre", "ID BDGEO": "114", "horodatage": "2021-04-05 09:11:23", "distance (en metres)": 101.29, "station": "PASTEUR-MEUNIERS", "marker-color": "#818181"}}, {"type": "Feature", "geometry": {"type": "Point", "coordinates": [2.32556, 48.821144]}, "properties": {"numparc": 1411, "etat de la localisation": "autre", "ID BDGEO": "223", "horodatage": "2021-04-05 09:57:17", "distance (en metres)": 97.5, "station": "PORTE D'ORLEANS", "marker-color": "#818181"}}, {"type": "Feature", "geometry": {"type": "Point", "coordinates": [2.317297, 48.797462]}, "properties": {"numparc": 1411, "etat de la localisation": "autre", "ID BDGEO": "114", "horodatage": "2021-04-05 10:23:44", "distance (en metres)": 96.75, "station": "PASTEUR-MEUNIERS", "marker-color": "#818181"}}, {"type": "Feature", "geometry": {"type": "Point", "coordinates": [2.325567, 48.821026]}, "properties": {"numparc": 1411, "etat de la localisation": "autre", "ID BDGEO": "223", "horodatage": "2021-04-05 11:12:27", "distance (en metres)": 109.03, "station": "PORTE D'ORLEANS", "marker-color": "#818181"}}, {"type": "Feature", "geometry": {"type": "Point", "coordinates": [2.317265, 48.797455]}, "properties": {"numparc": 1411, "etat de la localisation": "autre", "ID BDGEO": "114", "horodatage": "2021-04-05 11:37:14", "distance (en metres)": 97.86, "station": "PASTEUR-MEUNIERS", "marker-color": "#818181"}}, {"type": "Feature", "geometry": {"type": "Point", "coordinates": [2.325468, 48.821595]}, "properties": {"station": "PORTE D'ORLEANS.", "ID BDGEO": "2", "marker-color": "#56B3FF"}}, {"type": "Feature", "geometry": {"type": "Point", "coordinates": [2.317473, 48.798324]}, "properties": {"station": "PASTEUR-MEUNIERS", "ID BDGEO": "114", "marker-color": "#56B3FF"}}, {"type": "Feature", "geometry": {"type": "Point", "coordinates": [2.304163, 48.785208]}, "properties": {"station": "LES BLAGIS", "ID BDGEO": "90", "marker-color": "#56B3FF"}}, {"type": "Feature", "geometry": {"type": "Point", "coordinates": [2.324841, 48.821882]}, "properties": {"station": "PORTE D'ORLEANS", "ID BDGEO": "223", "marker-color": "#56B3FF"}}]}