{"type": "FeatureCollection", "features": [{"type": "Feature", "geometry": {"type": "Point", "coordinates": [2.330071, 48.822819]}, "properties": {"numparc": 1395, "etat de la localisation": "autre", "ID BDGEO": "724", "horodatage": "2021-04-23 16:40:02", "distance (en metres)": 87.17, "station": "MONTROUGE SORTIE", "marker-color": "#818181"}}, {"type": "Feature", "geometry": {"type": "Point", "coordinates": [2.293497, 48.781879]}, "properties": {"numparc": 1395, "etat de la localisation": "autre", "ID BDGEO": "483", "horodatage": "2021-04-23 18:27:18", "distance (en metres)": 46.98, "station": "RUE DU LYCEE", "marker-color": "#818181"}}, {"type": "Feature", "geometry": {"type": "Point", "coordinates": [2.329306, 48.82342]}, "properties": {"station": "MONTROUGE SORTIE", "ID BDGEO": "724", "marker-color": "#56B3FF"}}, {"type": "Feature", "geometry": {"type": "Point", "coordinates": [2.293312, 48.781475]}, "properties": {"station": "RUE DU LYCEE", "ID BDGEO": "483", "marker-color": "#56B3FF"}}]}