{"type": "FeatureCollection", "features": [{"type": "Feature", "geometry": {"type": "Point", "coordinates": [2.296596, 48.721294]}, "properties": {"numparc": 4878, "etat de la localisation": "autre", "ID BDGEO": "118", "horodatage": "2021-04-30 04:59:10", "distance (en metres)": 101.56, "station": "CENTRE BUS DE MASSY-SORTIE", "marker-color": "#818181"}}, {"type": "Feature", "geometry": {"type": "Point", "coordinates": [2.298206, 48.721626]}, "properties": {"numparc": 4878, "etat de la localisation": "autre", "ID BDGEO": "45", "horodatage": "2021-04-30 05:04:32", "distance (en metres)": 2872.84, "station": "VALLEE DE LA BIEVRE", "marker-color": "#818181"}}, {"type": "Feature", "geometry": {"type": "Point", "coordinates": [2.298206, 48.721626]}, "properties": {"numparc": 4878, "etat de la localisation": "autre", "ID BDGEO": "45", "horodatage": "2021-04-30 05:07:18", "distance (en metres)": 2872.84, "station": "VALLEE DE LA BIEVRE", "marker-color": "#818181"}}, {"type": "Feature", "geometry": {"type": "Point", "coordinates": [2.297646, 48.721298]}, "properties": {"numparc": 4877, "etat de la localisation": "autre", "ID BDGEO": "118", "horodatage": "2021-04-30 07:05:39", "distance (en metres)": 93.85, "station": "CENTRE BUS DE MASSY-SORTIE", "marker-color": "#818181"}}, {"type": "Feature", "geometry": {"type": "Point", "coordinates": [2.301161, 48.755589]}, "properties": {"numparc": 4874, "etat de la localisation": "autre", "ID BDGEO": "82", "horodatage": "2021-04-30 08:51:58", "distance (en metres)": 48.38, "station": "ANTONY RER", "marker-color": "#818181"}}, {"type": "Feature", "geometry": {"type": "Point", "coordinates": [2.296105, 48.755882]}, "properties": {"numparc": 4874, "etat de la localisation": "Deviation programmee", "ID BDGEO": "32", "horodatage": "2021-04-30 09:07:02", "distance (en metres)": 122.01, "station": "THEATRE-MAIRIE", "marker-color": "#56FF93"}}, {"type": "Feature", "geometry": {"type": "Point", "coordinates": [2.29607, 48.755825]}, "properties": {"numparc": 4877, "etat de la localisation": "Deviation programmee", "ID BDGEO": "32", "horodatage": "2021-04-30 09:21:22", "distance (en metres)": 117.57, "station": "THEATRE-MAIRIE", "marker-color": "#56FF93"}}, {"type": "Feature", "geometry": {"type": "Point", "coordinates": [2.29607, 48.755825]}, "properties": {"numparc": 4877, "etat de la localisation": "Deviation programmee", "ID BDGEO": "32", "horodatage": "2021-04-30 09:21:24", "distance (en metres)": 117.57, "station": "THEATRE-MAIRIE", "marker-color": "#56FF93"}}, {"type": "Feature", "geometry": {"type": "Point", "coordinates": [2.30145, 48.755535]}, "properties": {"numparc": 4874, "etat de la localisation": "autre", "ID BDGEO": "82", "horodatage": "2021-04-30 10:12:41", "distance (en metres)": 43.66, "station": "ANTONY RER", "marker-color": "#818181"}}, {"type": "Feature", "geometry": {"type": "Point", "coordinates": [2.301476, 48.755505]}, "properties": {"numparc": 4877, "etat de la localisation": "autre", "ID BDGEO": "82", "horodatage": "2021-04-30 10:23:13", "distance (en metres)": 41.14, "station": "ANTONY RER", "marker-color": "#818181"}}, {"type": "Feature", "geometry": {"type": "Point", "coordinates": [2.296157, 48.755951]}, "properties": {"numparc": 4877, "etat de la localisation": "Deviation programmee", "ID BDGEO": "32", "horodatage": "2021-04-30 11:53:55", "distance (en metres)": 127.38, "station": "THEATRE-MAIRIE", "marker-color": "#56FF93"}}, {"type": "Feature", "geometry": {"type": "Point", "coordinates": [2.296165, 48.755966]}, "properties": {"numparc": 4877, "etat de la localisation": "Deviation programmee", "ID BDGEO": "32", "horodatage": "2021-04-30 13:07:44", "distance (en metres)": 128.69, "station": "THEATRE-MAIRIE", "marker-color": "#56FF93"}}, {"type": "Feature", "geometry": {"type": "Point", "coordinates": [2.297907, 48.721146]}, "properties": {"numparc": 4874, "etat de la localisation": "autre", "ID BDGEO": "118", "horodatage": "2021-04-30 13:38:23", "distance (en metres)": 116.6, "station": "CENTRE BUS DE MASSY-SORTIE", "marker-color": "#818181"}}, {"type": "Feature", "geometry": {"type": "Point", "coordinates": [2.297247, 48.7221]}, "properties": {"station": "CENTRE BUS DE MASSY-SORTIE", "ID BDGEO": "118", "marker-color": "#56B3FF"}}, {"type": "Feature", "geometry": {"type": "Point", "coordinates": [2.267693, 48.737825]}, "properties": {"station": "VALLEE DE LA BIEVRE", "ID BDGEO": "45", "marker-color": "#56B3FF"}}, {"type": "Feature", "geometry": {"type": "Point", "coordinates": [2.301273, 48.75516]}, "properties": {"station": "ANTONY RER", "ID BDGEO": "82", "marker-color": "#56B3FF"}}, {"type": "Feature", "geometry": {"type": "Point", "coordinates": [2.296841, 48.754898]}, "properties": {"station": "THEATRE-MAIRIE", "ID BDGEO": "32", "marker-color": "#56B3FF"}}]}