{"type": "FeatureCollection", "features": [{"type": "Feature", "geometry": {"type": "Point", "coordinates": [2.407178, 48.8498]}, "properties": {"numparc": 610, "etat de la localisation": "autre", "ID BDGEO": "1134", "horodatage": "2021-06-25 06:48:11", "distance (en metres)": 13019.79, "station": "JULES VERNE LA DEFENSE#", "marker-color": "#818181"}}, {"type": "Feature", "geometry": {"type": "Point", "coordinates": [2.24095, 48.891694]}, "properties": {"station": "JULES VERNE LA DEFENSE#", "ID BDGEO": "1134", "marker-color": "#56B3FF"}}]}