{"type": "FeatureCollection", "features": [{"type": "Feature", "geometry": {"type": "Point", "coordinates": [2.258806, 48.780815]}, "properties": {"numparc": 5841, "etat de la localisation": "Delocalise", "ID BDGEO": "4894", "horodatage": "2021-04-23 12:39:46", "distance (en metres)": 94.82, "station": "LA POSTE", "marker-color": "#FF565E"}}, {"type": "Feature", "geometry": {"type": "Point", "coordinates": [2.2522, 48.782295]}, "properties": {"numparc": 5841, "etat de la localisation": "Deviation programmee", "ID BDGEO": "7550", "horodatage": "2021-04-23 12:42:29", "distance (en metres)": 127.97, "station": "PARC TECHNOLOGIQUE", "marker-color": "#56FF93"}}, {"type": "Feature", "geometry": {"type": "Point", "coordinates": [2.245992, 48.777763]}, "properties": {"numparc": 5841, "etat de la localisation": "Deviation programmee", "ID BDGEO": "4937", "horodatage": "2021-04-23 12:54:47", "distance (en metres)": 121.16, "station": "GALILEE", "marker-color": "#56FF93"}}, {"type": "Feature", "geometry": {"type": "Point", "coordinates": [2.25196, 48.782242]}, "properties": {"numparc": 5841, "etat de la localisation": "Deviation programmee", "ID BDGEO": "4899", "horodatage": "2021-04-23 12:56:43", "distance (en metres)": 95.68, "station": "PARC TECHNOLOGIQUE", "marker-color": "#56FF93"}}, {"type": "Feature", "geometry": {"type": "Point", "coordinates": [2.258861, 48.78083]}, "properties": {"numparc": 5841, "etat de la localisation": "Delocalise", "ID BDGEO": "4894", "horodatage": "2021-04-23 14:08:49", "distance (en metres)": 99.07, "station": "LA POSTE", "marker-color": "#FF565E"}}, {"type": "Feature", "geometry": {"type": "Point", "coordinates": [2.252206, 48.782272]}, "properties": {"numparc": 5841, "etat de la localisation": "Deviation programmee", "ID BDGEO": "7550", "horodatage": "2021-04-23 14:12:12", "distance (en metres)": 125.41, "station": "PARC TECHNOLOGIQUE", "marker-color": "#56FF93"}}, {"type": "Feature", "geometry": {"type": "Point", "coordinates": [2.295396, 48.756016]}, "properties": {"numparc": 5841, "etat de la localisation": "Deviation programmee", "ID BDGEO": "7549", "horodatage": "2021-04-23 14:53:33", "distance (en metres)": 148.51, "station": "THEATRE MAIRIE", "marker-color": "#56FF93"}}, {"type": "Feature", "geometry": {"type": "Point", "coordinates": [2.258786, 48.780769]}, "properties": {"numparc": 5841, "etat de la localisation": "autre", "ID BDGEO": "4894", "horodatage": "2021-04-23 15:31:17", "distance (en metres)": 90.73, "station": "LA POSTE", "marker-color": "#818181"}}, {"type": "Feature", "geometry": {"type": "Point", "coordinates": [2.245979, 48.777763]}, "properties": {"numparc": 5841, "etat de la localisation": "Deviation programmee", "ID BDGEO": "4937", "horodatage": "2021-04-23 15:43:26", "distance (en metres)": 121.55, "station": "GALILEE", "marker-color": "#56FF93"}}, {"type": "Feature", "geometry": {"type": "Point", "coordinates": [2.251904, 48.782207]}, "properties": {"numparc": 5841, "etat de la localisation": "Deviation programmee", "ID BDGEO": "4899", "horodatage": "2021-04-23 15:45:29", "distance (en metres)": 96.39, "station": "PARC TECHNOLOGIQUE", "marker-color": "#56FF93"}}, {"type": "Feature", "geometry": {"type": "Point", "coordinates": [2.290818, 48.759029]}, "properties": {"numparc": 5841, "etat de la localisation": "Deviation programmee", "ID BDGEO": "6967", "horodatage": "2021-04-23 16:17:35", "distance (en metres)": 843.32, "station": "GARE D'ANTONY#", "marker-color": "#56FF93"}}, {"type": "Feature", "geometry": {"type": "Point", "coordinates": [2.257748, 48.780324]}, "properties": {"station": "LA POSTE", "ID BDGEO": "4894", "marker-color": "#56B3FF"}}, {"type": "Feature", "geometry": {"type": "Point", "coordinates": [2.252742, 48.781201]}, "properties": {"station": "PARC TECHNOLOGIQUE", "ID BDGEO": "7550", "marker-color": "#56B3FF"}}, {"type": "Feature", "geometry": {"type": "Point", "coordinates": [2.246657, 48.776765]}, "properties": {"station": "GALILEE", "ID BDGEO": "4937", "marker-color": "#56B3FF"}}, {"type": "Feature", "geometry": {"type": "Point", "coordinates": [2.252945, 48.781677]}, "properties": {"station": "PARC TECHNOLOGIQUE", "ID BDGEO": "4899", "marker-color": "#56B3FF"}}, {"type": "Feature", "geometry": {"type": "Point", "coordinates": [2.296705, 48.754997]}, "properties": {"station": "THEATRE MAIRIE", "ID BDGEO": "7549", "marker-color": "#56B3FF"}}, {"type": "Feature", "geometry": {"type": "Point", "coordinates": [2.300973, 48.755466]}, "properties": {"station": "GARE D'ANTONY#", "ID BDGEO": "6967", "marker-color": "#56B3FF"}}]}