{"type": "FeatureCollection", "features": [{"type": "Feature", "geometry": {"type": "Point", "coordinates": [2.324461, 48.875153]}, "properties": {"numparc": 599, "etat de la localisation": "autre", "ID BDGEO": "21939", "horodatage": "2021-04-29 01:09:54", "distance (en metres)": 91.4, "station": "GARE SAINT-LAZARE", "marker-color": "#818181"}}, {"type": "Feature", "geometry": {"type": "Point", "coordinates": [2.32521, 48.874495]}, "properties": {"station": "GARE SAINT-LAZARE", "ID BDGEO": "21939", "marker-color": "#56B3FF"}}]}