{"type": "FeatureCollection", "features": [{"type": "Feature", "geometry": {"type": "Point", "coordinates": [2.297069, 48.720947]}, "properties": {"numparc": 5858, "etat de la localisation": "autre", "ID BDGEO": "101", "horodatage": "2021-05-16 12:28:47", "distance (en metres)": 75.36, "station": "CENTRE BUS DE MASSY-SORTIE", "marker-color": "#818181"}}, {"type": "Feature", "geometry": {"type": "Point", "coordinates": [2.296939, 48.72131]}, "properties": {"numparc": 5858, "etat de la localisation": "autre", "ID BDGEO": "101", "horodatage": "2021-05-16 12:32:38", "distance (en metres)": 60.92, "station": "CENTRE BUS DE MASSY-SORTIE", "marker-color": "#818181"}}, {"type": "Feature", "geometry": {"type": "Point", "coordinates": [2.296934, 48.72126]}, "properties": {"numparc": 5858, "etat de la localisation": "autre", "ID BDGEO": "101", "horodatage": "2021-05-16 12:34:39", "distance (en metres)": 63.03, "station": "CENTRE BUS DE MASSY-SORTIE", "marker-color": "#818181"}}, {"type": "Feature", "geometry": {"type": "Point", "coordinates": [2.298281, 48.721699]}, "properties": {"numparc": 5858, "etat de la localisation": "autre", "ID BDGEO": "101", "horodatage": "2021-05-16 12:35:45", "distance (en metres)": 47.84, "station": "CENTRE BUS DE MASSY-SORTIE", "marker-color": "#818181"}}, {"type": "Feature", "geometry": {"type": "Point", "coordinates": [2.297121, 48.721577]}, "properties": {"numparc": 5862, "etat de la localisation": "autre", "ID BDGEO": "101", "horodatage": "2021-05-16 18:10:57", "distance (en metres)": 46.94, "station": "CENTRE BUS DE MASSY-SORTIE", "marker-color": "#818181"}}, {"type": "Feature", "geometry": {"type": "Point", "coordinates": [2.297137, 48.721527]}, "properties": {"numparc": 5862, "etat de la localisation": "autre", "ID BDGEO": "101", "horodatage": "2021-05-16 18:14:17", "distance (en metres)": 44.59, "station": "CENTRE BUS DE MASSY-SORTIE", "marker-color": "#818181"}}, {"type": "Feature", "geometry": {"type": "Point", "coordinates": [2.297737, 48.721462]}, "properties": {"station": "CENTRE BUS DE MASSY-SORTIE", "ID BDGEO": "101", "marker-color": "#56B3FF"}}]}