{"type": "FeatureCollection", "features": [{"type": "Feature", "geometry": {"type": "Point", "coordinates": [2.427676, 48.878906]}, "properties": {"numparc": 4949, "etat de la localisation": "autre", "ID BDGEO": "771", "horodatage": "2021-05-10 13:25:02", "distance (en metres)": 104.69, "station": "DEPOT LES LILAS (S)", "marker-color": "#818181"}}, {"type": "Feature", "geometry": {"type": "Point", "coordinates": [2.42908, 48.879089]}, "properties": {"station": "DEPOT LES LILAS (S)", "ID BDGEO": "771", "marker-color": "#56B3FF"}}]}