{"type": "FeatureCollection", "features": [{"type": "Feature", "geometry": {"type": "Point", "coordinates": [2.441473, 48.772236]}, "properties": {"numparc": 2812, "etat de la localisation": "autre", "ID BDGEO": "3286", "horodatage": "2021-05-17 10:06:59", "distance (en metres)": 20239.17, "station": "LES ROSIERS", "marker-color": "#818181"}}, {"type": "Feature", "geometry": {"type": "Point", "coordinates": [2.441473, 48.772236]}, "properties": {"numparc": 2812, "etat de la localisation": "autre", "ID BDGEO": "3286", "horodatage": "2021-05-17 10:08:00", "distance (en metres)": 20239.17, "station": "LES ROSIERS", "marker-color": "#818181"}}, {"type": "Feature", "geometry": {"type": "Point", "coordinates": [2.441473, 48.772236]}, "properties": {"numparc": 2812, "etat de la localisation": "autre", "ID BDGEO": "3286", "horodatage": "2021-05-17 10:09:39", "distance (en metres)": 20239.17, "station": "LES ROSIERS", "marker-color": "#818181"}}, {"type": "Feature", "geometry": {"type": "Point", "coordinates": [2.441477, 48.772236]}, "properties": {"numparc": 2812, "etat de la localisation": "autre", "ID BDGEO": "3286", "horodatage": "2021-05-17 10:10:50", "distance (en metres)": 20239.39, "station": "LES ROSIERS", "marker-color": "#818181"}}, {"type": "Feature", "geometry": {"type": "Point", "coordinates": [2.441568, 48.772026]}, "properties": {"numparc": 2812, "etat de la localisation": "autre", "ID BDGEO": "3286", "horodatage": "2021-05-17 10:14:27", "distance (en metres)": 20259.48, "station": "LES ROSIERS", "marker-color": "#818181"}}, {"type": "Feature", "geometry": {"type": "Point", "coordinates": [2.441863, 48.772301]}, "properties": {"numparc": 2812, "etat de la localisation": "autre", "ID BDGEO": "3286", "horodatage": "2021-05-17 10:16:40", "distance (en metres)": 20256.5, "station": "LES ROSIERS", "marker-color": "#818181"}}, {"type": "Feature", "geometry": {"type": "Point", "coordinates": [2.441418, 48.771866]}, "properties": {"numparc": 2812, "etat de la localisation": "autre", "ID BDGEO": "3286", "horodatage": "2021-05-17 10:23:49", "distance (en metres)": 20262.46, "station": "LES ROSIERS", "marker-color": "#818181"}}, {"type": "Feature", "geometry": {"type": "Point", "coordinates": [2.441515, 48.772022]}, "properties": {"numparc": 2812, "etat de la localisation": "autre", "ID BDGEO": "3286", "horodatage": "2021-05-17 11:13:35", "distance (en metres)": 20256.78, "station": "LES ROSIERS", "marker-color": "#818181"}}, {"type": "Feature", "geometry": {"type": "Point", "coordinates": [2.441515, 48.772022]}, "properties": {"numparc": 2812, "etat de la localisation": "autre", "ID BDGEO": "3286", "horodatage": "2021-05-17 11:35:43", "distance (en metres)": 20256.78, "station": "LES ROSIERS", "marker-color": "#818181"}}, {"type": "Feature", "geometry": {"type": "Point", "coordinates": [2.441515, 48.772022]}, "properties": {"numparc": 2812, "etat de la localisation": "autre", "ID BDGEO": "3286", "horodatage": "2021-05-17 11:36:12", "distance (en metres)": 20256.78, "station": "LES ROSIERS", "marker-color": "#818181"}}, {"type": "Feature", "geometry": {"type": "Point", "coordinates": [2.441515, 48.772022]}, "properties": {"numparc": 2812, "etat de la localisation": "autre", "ID BDGEO": "3286", "horodatage": "2021-05-17 11:36:28", "distance (en metres)": 20256.78, "station": "LES ROSIERS", "marker-color": "#818181"}}, {"type": "Feature", "geometry": {"type": "Point", "coordinates": [2.441515, 48.772022]}, "properties": {"numparc": 2812, "etat de la localisation": "autre", "ID BDGEO": "3286", "horodatage": "2021-05-17 11:39:17", "distance (en metres)": 20256.78, "station": "LES ROSIERS", "marker-color": "#818181"}}, {"type": "Feature", "geometry": {"type": "Point", "coordinates": [2.441515, 48.772022]}, "properties": {"numparc": 2812, "etat de la localisation": "autre", "ID BDGEO": "3286", "horodatage": "2021-05-17 11:40:09", "distance (en metres)": 20256.78, "station": "LES ROSIERS", "marker-color": "#818181"}}, {"type": "Feature", "geometry": {"type": "Point", "coordinates": [2.443133, 48.772247]}, "properties": {"numparc": 2812, "etat de la localisation": "autre", "ID BDGEO": "3286", "horodatage": "2021-05-17 11:51:33", "distance (en metres)": 20331.95, "station": "LES ROSIERS", "marker-color": "#818181"}}, {"type": "Feature", "geometry": {"type": "Point", "coordinates": [2.443356, 48.772217]}, "properties": {"numparc": 2812, "etat de la localisation": "autre", "ID BDGEO": "3286", "horodatage": "2021-05-17 16:01:46", "distance (en metres)": 20346.67, "station": "LES ROSIERS", "marker-color": "#818181"}}, {"type": "Feature", "geometry": {"type": "Point", "coordinates": [2.228908, 48.888637]}, "properties": {"station": "LES ROSIERS", "ID BDGEO": "3286", "marker-color": "#56B3FF"}}]}