{"type": "FeatureCollection", "features": [{"type": "Feature", "geometry": {"type": "Point", "coordinates": [2.297525, 48.721004]}, "properties": {"numparc": 4874, "etat de la localisation": "autre", "ID BDGEO": "118", "horodatage": "2021-04-25 12:13:46", "distance (en metres)": 123.56, "station": "CENTRE BUS DE MASSY-SORTIE", "marker-color": "#818181"}}, {"type": "Feature", "geometry": {"type": "Point", "coordinates": [2.297525, 48.721004]}, "properties": {"numparc": 4874, "etat de la localisation": "Delocalise", "ID BDGEO": "118", "horodatage": "2021-04-25 12:18:00", "distance (en metres)": 123.56, "station": "CENTRE BUS DE MASSY-SORTIE", "marker-color": "#FF565E"}}, {"type": "Feature", "geometry": {"type": "Point", "coordinates": [2.297762, 48.721169]}, "properties": {"numparc": 4874, "etat de la localisation": "autre", "ID BDGEO": "45", "horodatage": "2021-04-25 12:28:47", "distance (en metres)": 2879.96, "station": "VALLEE DE LA BIEVRE", "marker-color": "#818181"}}, {"type": "Feature", "geometry": {"type": "Point", "coordinates": [2.298263, 48.719105]}, "properties": {"numparc": 4874, "etat de la localisation": "autre", "ID BDGEO": "45", "horodatage": "2021-04-25 12:30:00", "distance (en metres)": 3059.51, "station": "VALLEE DE LA BIEVRE", "marker-color": "#818181"}}, {"type": "Feature", "geometry": {"type": "Point", "coordinates": [2.296954, 48.721321]}, "properties": {"numparc": 4877, "etat de la localisation": "autre", "ID BDGEO": "118", "horodatage": "2021-04-25 12:48:00", "distance (en metres)": 89.25, "station": "CENTRE BUS DE MASSY-SORTIE", "marker-color": "#818181"}}, {"type": "Feature", "geometry": {"type": "Point", "coordinates": [2.301461, 48.755627]}, "properties": {"numparc": 4882, "etat de la localisation": "autre", "ID BDGEO": "82", "horodatage": "2021-04-25 16:36:48", "distance (en metres)": 53.72, "station": "ANTONY RER", "marker-color": "#818181"}}, {"type": "Feature", "geometry": {"type": "Point", "coordinates": [2.264126, 48.746281]}, "properties": {"numparc": 4874, "etat de la localisation": "autre", "ID BDGEO": "134", "horodatage": "2021-04-25 17:43:55", "distance (en metres)": 51.4, "station": "D'ESTIENNE D'ORVES - GENERAL LECLERC", "marker-color": "#818181"}}, {"type": "Feature", "geometry": {"type": "Point", "coordinates": [2.297993, 48.7215]}, "properties": {"numparc": 4874, "etat de la localisation": "autre", "ID BDGEO": "118", "horodatage": "2021-04-25 18:43:33", "distance (en metres)": 86.27, "station": "CENTRE BUS DE MASSY-SORTIE", "marker-color": "#818181"}}, {"type": "Feature", "geometry": {"type": "Point", "coordinates": [2.297992, 48.721569]}, "properties": {"numparc": 4882, "etat de la localisation": "autre", "ID BDGEO": "118", "horodatage": "2021-04-25 18:45:15", "distance (en metres)": 80.44, "station": "CENTRE BUS DE MASSY-SORTIE", "marker-color": "#818181"}}, {"type": "Feature", "geometry": {"type": "Point", "coordinates": [2.29837, 48.721825]}, "properties": {"numparc": 4874, "etat de la localisation": "autre", "ID BDGEO": "118", "horodatage": "2021-04-25 18:45:34", "distance (en metres)": 87.86, "station": "CENTRE BUS DE MASSY-SORTIE", "marker-color": "#818181"}}, {"type": "Feature", "geometry": {"type": "Point", "coordinates": [2.297117, 48.721649]}, "properties": {"numparc": 4882, "etat de la localisation": "autre", "ID BDGEO": "118", "horodatage": "2021-04-25 18:47:34", "distance (en metres)": 51.05, "station": "CENTRE BUS DE MASSY-SORTIE", "marker-color": "#818181"}}, {"type": "Feature", "geometry": {"type": "Point", "coordinates": [2.298014, 48.721516]}, "properties": {"numparc": 4877, "etat de la localisation": "autre", "ID BDGEO": "118", "horodatage": "2021-04-25 19:06:34", "distance (en metres)": 85.91, "station": "CENTRE BUS DE MASSY-SORTIE", "marker-color": "#818181"}}, {"type": "Feature", "geometry": {"type": "Point", "coordinates": [2.297247, 48.7221]}, "properties": {"station": "CENTRE BUS DE MASSY-SORTIE", "ID BDGEO": "118", "marker-color": "#56B3FF"}}, {"type": "Feature", "geometry": {"type": "Point", "coordinates": [2.267693, 48.737825]}, "properties": {"station": "VALLEE DE LA BIEVRE", "ID BDGEO": "45", "marker-color": "#56B3FF"}}, {"type": "Feature", "geometry": {"type": "Point", "coordinates": [2.301273, 48.75516]}, "properties": {"station": "ANTONY RER", "ID BDGEO": "82", "marker-color": "#56B3FF"}}, {"type": "Feature", "geometry": {"type": "Point", "coordinates": [2.264746, 48.746065]}, "properties": {"station": "D'ESTIENNE D'ORVES - GENERAL LECLERC", "ID BDGEO": "134", "marker-color": "#56B3FF"}}]}