{"type": "FeatureCollection", "features": [{"type": "Feature", "geometry": {"type": "Point", "coordinates": [2.296877, 48.721333]}, "properties": {"numparc": 5857, "etat de la localisation": "autre", "ID BDGEO": "101", "horodatage": "2021-04-26 00:34:58", "distance (en metres)": 64.68, "station": "CENTRE BUS DE MASSY-SORTIE", "marker-color": "#818181"}}, {"type": "Feature", "geometry": {"type": "Point", "coordinates": [2.298154, 48.721699]}, "properties": {"numparc": 5850, "etat de la localisation": "autre", "ID BDGEO": "101", "horodatage": "2021-04-26 01:28:53", "distance (en metres)": 40.39, "station": "CENTRE BUS DE MASSY-SORTIE", "marker-color": "#818181"}}, {"type": "Feature", "geometry": {"type": "Point", "coordinates": [2.298154, 48.721699]}, "properties": {"numparc": 5850, "etat de la localisation": "autre", "ID BDGEO": "101", "horodatage": "2021-04-26 01:28:59", "distance (en metres)": 40.39, "station": "CENTRE BUS DE MASSY-SORTIE", "marker-color": "#818181"}}, {"type": "Feature", "geometry": {"type": "Point", "coordinates": [2.298154, 48.721699]}, "properties": {"numparc": 5850, "etat de la localisation": "autre", "ID BDGEO": "101", "horodatage": "2021-04-26 01:29:09", "distance (en metres)": 40.39, "station": "CENTRE BUS DE MASSY-SORTIE", "marker-color": "#818181"}}, {"type": "Feature", "geometry": {"type": "Point", "coordinates": [2.298154, 48.721699]}, "properties": {"numparc": 5850, "etat de la localisation": "autre", "ID BDGEO": "101", "horodatage": "2021-04-26 01:29:16", "distance (en metres)": 40.39, "station": "CENTRE BUS DE MASSY-SORTIE", "marker-color": "#818181"}}, {"type": "Feature", "geometry": {"type": "Point", "coordinates": [2.298154, 48.721699]}, "properties": {"numparc": 5850, "etat de la localisation": "autre", "ID BDGEO": "101", "horodatage": "2021-04-26 01:29:37", "distance (en metres)": 40.39, "station": "CENTRE BUS DE MASSY-SORTIE", "marker-color": "#818181"}}, {"type": "Feature", "geometry": {"type": "Point", "coordinates": [2.297845, 48.722145]}, "properties": {"numparc": 5850, "etat de la localisation": "autre", "ID BDGEO": "101", "horodatage": "2021-04-26 01:32:11", "distance (en metres)": 76.36, "station": "CENTRE BUS DE MASSY-SORTIE", "marker-color": "#818181"}}, {"type": "Feature", "geometry": {"type": "Point", "coordinates": [2.297737, 48.721462]}, "properties": {"station": "CENTRE BUS DE MASSY-SORTIE", "ID BDGEO": "101", "marker-color": "#56B3FF"}}]}