{"type": "FeatureCollection", "features": [{"type": "Feature", "geometry": {"type": "Point", "coordinates": [2.427391, 48.879234]}, "properties": {"numparc": 6145, "etat de la localisation": "autre", "ID BDGEO": "2", "horodatage": "2021-06-12 05:07:23", "distance (en metres)": 492.19, "station": "LOUISE MICHEL", "marker-color": "#818181"}}, {"type": "Feature", "geometry": {"type": "Point", "coordinates": [2.431827, 48.875905]}, "properties": {"station": "LOUISE MICHEL", "ID BDGEO": "2", "marker-color": "#56B3FF"}}]}