{"type": "FeatureCollection", "features": [{"type": "Feature", "geometry": {"type": "Point", "coordinates": [2.642566, 48.833549]}, "properties": {"numparc": 4983, "etat de la localisation": "autre", "ID BDGEO": "70", "horodatage": "2021-06-27 18:44:54", "distance (en metres)": 1062.32, "station": "TORCY RER#", "marker-color": "#818181"}}, {"type": "Feature", "geometry": {"type": "Point", "coordinates": [2.654139, 48.839363]}, "properties": {"numparc": 4983, "etat de la localisation": "autre", "ID BDGEO": "70", "horodatage": "2021-06-27 19:01:22", "distance (en metres)": 73.74, "station": "TORCY RER#", "marker-color": "#818181"}}, {"type": "Feature", "geometry": {"type": "Point", "coordinates": [2.654136, 48.839359]}, "properties": {"numparc": 4983, "etat de la localisation": "autre", "ID BDGEO": "70", "horodatage": "2021-06-27 19:01:27", "distance (en metres)": 73.49, "station": "TORCY RER#", "marker-color": "#818181"}}, {"type": "Feature", "geometry": {"type": "Point", "coordinates": [2.65421, 48.839321]}, "properties": {"numparc": 4983, "etat de la localisation": "autre", "ID BDGEO": "70", "horodatage": "2021-06-27 20:01:43", "distance (en metres)": 67.02, "station": "TORCY RER#", "marker-color": "#818181"}}, {"type": "Feature", "geometry": {"type": "Point", "coordinates": [2.642545, 48.833576]}, "properties": {"numparc": 4983, "etat de la localisation": "autre", "ID BDGEO": "70", "horodatage": "2021-06-27 20:15:32", "distance (en metres)": 1061.96, "station": "TORCY RER#", "marker-color": "#818181"}}, {"type": "Feature", "geometry": {"type": "Point", "coordinates": [2.654686, 48.838806]}, "properties": {"station": "TORCY RER#", "ID BDGEO": "70", "marker-color": "#56B3FF"}}]}