{"type": "FeatureCollection", "features": [{"type": "Feature", "geometry": {"type": "Point", "coordinates": [2.348806, 48.857529]}, "properties": {"numparc": 6145, "etat de la localisation": "Delocalise", "ID BDGEO": "17292", "horodatage": "2021-06-05 01:02:56", "distance (en metres)": 7153.77, "station": "PORTE DE ST-CLOUD", "marker-color": "#FF565E"}}, {"type": "Feature", "geometry": {"type": "Point", "coordinates": [2.326335, 48.846344]}, "properties": {"numparc": 6145, "etat de la localisation": "autre", "ID BDGEO": "17292", "horodatage": "2021-06-05 01:15:37", "distance (en metres)": 5249.45, "station": "PORTE DE ST-CLOUD", "marker-color": "#818181"}}, {"type": "Feature", "geometry": {"type": "Point", "coordinates": [2.300704, 48.847912]}, "properties": {"numparc": 6145, "etat de la localisation": "autre", "ID BDGEO": "17292", "horodatage": "2021-06-05 01:22:07", "distance (en metres)": 3476.86, "station": "PORTE DE ST-CLOUD", "marker-color": "#818181"}}, {"type": "Feature", "geometry": {"type": "Point", "coordinates": [2.278842, 48.851215]}, "properties": {"numparc": 6145, "etat de la localisation": "autre", "ID BDGEO": "17292", "horodatage": "2021-06-05 01:27:24", "distance (en metres)": 2262.0, "station": "PORTE DE ST-CLOUD", "marker-color": "#818181"}}, {"type": "Feature", "geometry": {"type": "Point", "coordinates": [2.230116, 48.829208]}, "properties": {"numparc": 6145, "etat de la localisation": "autre", "ID BDGEO": "22551", "horodatage": "2021-06-05 01:38:49", "distance (en metres)": 111.4, "station": "PONT DE SEVRES", "marker-color": "#818181"}}, {"type": "Feature", "geometry": {"type": "Point", "coordinates": [2.230116, 48.829208]}, "properties": {"numparc": 6145, "etat de la localisation": "autre", "ID BDGEO": "22551", "horodatage": "2021-06-05 01:41:06", "distance (en metres)": 111.4, "station": "PONT DE SEVRES", "marker-color": "#818181"}}, {"type": "Feature", "geometry": {"type": "Point", "coordinates": [2.300947, 48.847767]}, "properties": {"numparc": 6145, "etat de la localisation": "autre", "ID BDGEO": "17260", "horodatage": "2021-06-05 02:00:19", "distance (en metres)": 49.7, "station": "CAMBRONNE", "marker-color": "#818181"}}, {"type": "Feature", "geometry": {"type": "Point", "coordinates": [2.31965, 48.841743]}, "properties": {"numparc": 6145, "etat de la localisation": "autre", "ID BDGEO": "21015", "horodatage": "2021-06-05 02:06:14", "distance (en metres)": 51.73, "station": "GARE MONTPARNASSE", "marker-color": "#818181"}}, {"type": "Feature", "geometry": {"type": "Point", "coordinates": [2.319699, 48.841755]}, "properties": {"numparc": 6145, "etat de la localisation": "autre", "ID BDGEO": "21015", "horodatage": "2021-06-05 02:07:08", "distance (en metres)": 47.92, "station": "GARE MONTPARNASSE", "marker-color": "#818181"}}, {"type": "Feature", "geometry": {"type": "Point", "coordinates": [2.346689, 48.856476]}, "properties": {"numparc": 6145, "etat de la localisation": "autre", "ID BDGEO": "17245", "horodatage": "2021-06-05 02:17:16", "distance (en metres)": 82.83, "station": "CITE-PALAIS DE JUSTICE", "marker-color": "#818181"}}, {"type": "Feature", "geometry": {"type": "Point", "coordinates": [2.255836, 48.837628]}, "properties": {"station": "PORTE DE ST-CLOUD", "ID BDGEO": "17292", "marker-color": "#56B3FF"}}, {"type": "Feature", "geometry": {"type": "Point", "coordinates": [2.231345, 48.829799]}, "properties": {"station": "PONT DE SEVRES", "ID BDGEO": "22551", "marker-color": "#56B3FF"}}, {"type": "Feature", "geometry": {"type": "Point", "coordinates": [2.300269, 48.847743]}, "properties": {"station": "CAMBRONNE", "ID BDGEO": "17260", "marker-color": "#56B3FF"}}, {"type": "Feature", "geometry": {"type": "Point", "coordinates": [2.320289, 48.841942]}, "properties": {"station": "GARE MONTPARNASSE", "ID BDGEO": "21015", "marker-color": "#56B3FF"}}, {"type": "Feature", "geometry": {"type": "Point", "coordinates": [2.346271, 48.855784]}, "properties": {"station": "CITE-PALAIS DE JUSTICE", "ID BDGEO": "17245", "marker-color": "#56B3FF"}}]}