{"type": "FeatureCollection", "features": [{"type": "Feature", "geometry": {"type": "Point", "coordinates": [2.407878, 48.849308]}, "properties": {"numparc": 681, "etat de la localisation": "autre", "ID BDGEO": "429", "horodatage": "2021-05-05 06:13:57", "distance (en metres)": 1713.2, "station": "WATTIGNIES-GRAVELLE", "marker-color": "#818181"}}, {"type": "Feature", "geometry": {"type": "Point", "coordinates": [2.397377, 48.835538]}, "properties": {"station": "WATTIGNIES-GRAVELLE", "ID BDGEO": "429", "marker-color": "#56B3FF"}}]}