{"type": "FeatureCollection", "features": [{"type": "Feature", "geometry": {"type": "Point", "coordinates": [2.298924, 48.722771]}, "properties": {"numparc": 4845, "etat de la localisation": "autre", "ID BDGEO": "52", "horodatage": "2021-04-01 05:20:19", "distance (en metres)": 4816.87, "station": "ROBERT SCHUMAN", "marker-color": "#818181"}}, {"type": "Feature", "geometry": {"type": "Point", "coordinates": [2.333182, 48.832691]}, "properties": {"numparc": 4845, "etat de la localisation": "autre", "ID BDGEO": "86", "horodatage": "2021-04-01 06:43:03", "distance (en metres)": 7940.98, "station": "RUNGIS-MARCHE INTERNATIONAL#", "marker-color": "#818181"}}, {"type": "Feature", "geometry": {"type": "Point", "coordinates": [2.333182, 48.832691]}, "properties": {"numparc": 4845, "etat de la localisation": "autre", "ID BDGEO": "86", "horodatage": "2021-04-01 06:43:29", "distance (en metres)": 7940.98, "station": "RUNGIS-MARCHE INTERNATIONAL#", "marker-color": "#818181"}}, {"type": "Feature", "geometry": {"type": "Point", "coordinates": [2.333182, 48.832691]}, "properties": {"numparc": 4845, "etat de la localisation": "autre", "ID BDGEO": "86", "horodatage": "2021-04-01 06:44:57", "distance (en metres)": 7940.98, "station": "RUNGIS-MARCHE INTERNATIONAL#", "marker-color": "#818181"}}, {"type": "Feature", "geometry": {"type": "Point", "coordinates": [2.333816, 48.834686]}, "properties": {"numparc": 5858, "etat de la localisation": "autre", "ID BDGEO": "2", "horodatage": "2021-04-01 07:27:38", "distance (en metres)": 174.52, "station": "DENFERT ROCHEREAU-METRO-RER", "marker-color": "#818181"}}, {"type": "Feature", "geometry": {"type": "Point", "coordinates": [2.34354, 48.760464]}, "properties": {"numparc": 5858, "etat de la localisation": "autre", "ID BDGEO": "8", "horodatage": "2021-04-01 07:46:32", "distance (en metres)": 45.71, "station": "PORTE DE L'HAY-LYONNAIS", "marker-color": "#818181"}}, {"type": "Feature", "geometry": {"type": "Point", "coordinates": [2.351906, 48.761806]}, "properties": {"numparc": 5858, "etat de la localisation": "Delocalise", "ID BDGEO": "1", "horodatage": "2021-04-01 08:04:09", "distance (en metres)": 478.6, "station": "RUNGIS-MARCHE INTERNATIONAL", "marker-color": "#FF565E"}}, {"type": "Feature", "geometry": {"type": "Point", "coordinates": [2.3331, 48.832954]}, "properties": {"numparc": 5858, "etat de la localisation": "autre", "ID BDGEO": "2", "horodatage": "2021-04-01 08:35:35", "distance (en metres)": 139.04, "station": "DENFERT ROCHEREAU-METRO-RER", "marker-color": "#818181"}}, {"type": "Feature", "geometry": {"type": "Point", "coordinates": [2.345015, 48.819004]}, "properties": {"numparc": 5858, "etat de la localisation": "autre", "ID BDGEO": "7", "horodatage": "2021-04-01 08:52:36", "distance (en metres)": 54.86, "station": "STADE CHARLETY-PORTE DE GENTILLY", "marker-color": "#818181"}}, {"type": "Feature", "geometry": {"type": "Point", "coordinates": [2.343589, 48.76046]}, "properties": {"numparc": 5858, "etat de la localisation": "autre", "ID BDGEO": "8", "horodatage": "2021-04-01 09:01:01", "distance (en metres)": 47.87, "station": "PORTE DE L'HAY-LYONNAIS", "marker-color": "#818181"}}, {"type": "Feature", "geometry": {"type": "Point", "coordinates": [2.354366, 48.745996]}, "properties": {"station": "ROBERT SCHUMAN", "ID BDGEO": "52", "marker-color": "#56B3FF"}}, {"type": "Feature", "geometry": {"type": "Point", "coordinates": [2.358056, 48.763181]}, "properties": {"station": "RUNGIS-MARCHE INTERNATIONAL#", "ID BDGEO": "86", "marker-color": "#56B3FF"}}, {"type": "Feature", "geometry": {"type": "Point", "coordinates": [2.334927, 48.833297]}, "properties": {"station": "DENFERT ROCHEREAU-METRO-RER", "ID BDGEO": "2", "marker-color": "#56B3FF"}}, {"type": "Feature", "geometry": {"type": "Point", "coordinates": [2.34325, 48.760828]}, "properties": {"station": "PORTE DE L'HAY-LYONNAIS", "ID BDGEO": "8", "marker-color": "#56B3FF"}}, {"type": "Feature", "geometry": {"type": "Point", "coordinates": [2.358137, 48.763091]}, "properties": {"station": "RUNGIS-MARCHE INTERNATIONAL", "ID BDGEO": "1", "marker-color": "#56B3FF"}}, {"type": "Feature", "geometry": {"type": "Point", "coordinates": [2.344278, 48.818917]}, "properties": {"station": "STADE CHARLETY-PORTE DE GENTILLY", "ID BDGEO": "7", "marker-color": "#56B3FF"}}]}