{"type": "FeatureCollection", "features": [{"type": "Feature", "geometry": {"type": "Point", "coordinates": [2.309969, 48.887939]}, "properties": {"numparc": 1388, "etat de la localisation": "autre", "ID BDGEO": "138", "horodatage": "2021-06-13 13:44:47", "distance (en metres)": 44.27, "station": "PEREIRE SAUSSURE", "marker-color": "#818181"}}, {"type": "Feature", "geometry": {"type": "Point", "coordinates": [2.326046, 48.875469]}, "properties": {"numparc": 1388, "etat de la localisation": "autre", "ID BDGEO": "38", "horodatage": "2021-06-13 13:55:58", "distance (en metres)": 49.03, "station": "GARE SAINT-LAZARE", "marker-color": "#818181"}}, {"type": "Feature", "geometry": {"type": "Point", "coordinates": [2.32919, 48.84935]}, "properties": {"numparc": 1388, "etat de la localisation": "Delocalise", "ID BDGEO": "7", "horodatage": "2021-06-13 14:44:50", "distance (en metres)": 139.08, "station": "RUE DU CHERCHE MIDI", "marker-color": "#FF565E"}}, {"type": "Feature", "geometry": {"type": "Point", "coordinates": [2.326144, 48.85413]}, "properties": {"numparc": 1388, "etat de la localisation": "autre", "ID BDGEO": "9", "horodatage": "2021-06-13 14:51:42", "distance (en metres)": 62.35, "station": "CHARLOTTE PERRIAND", "marker-color": "#818181"}}, {"type": "Feature", "geometry": {"type": "Point", "coordinates": [2.278111, 48.897415]}, "properties": {"numparc": 1388, "etat de la localisation": "autre", "ID BDGEO": "109", "horodatage": "2021-06-13 15:38:59", "distance (en metres)": 88.86, "station": "PONT DE LEVALLOIS", "marker-color": "#818181"}}, {"type": "Feature", "geometry": {"type": "Point", "coordinates": [2.278186, 48.897366]}, "properties": {"numparc": 1388, "etat de la localisation": "autre", "ID BDGEO": "109", "horodatage": "2021-06-13 18:03:39", "distance (en metres)": 87.53, "station": "PONT DE LEVALLOIS", "marker-color": "#818181"}}, {"type": "Feature", "geometry": {"type": "Point", "coordinates": [2.310062, 48.887825]}, "properties": {"numparc": 1388, "etat de la localisation": "autre", "ID BDGEO": "138", "horodatage": "2021-06-13 18:33:52", "distance (en metres)": 45.74, "station": "PEREIRE SAUSSURE", "marker-color": "#818181"}}, {"type": "Feature", "geometry": {"type": "Point", "coordinates": [2.322504, 48.867302]}, "properties": {"numparc": 1388, "etat de la localisation": "autre", "ID BDGEO": "42", "horodatage": "2021-06-13 18:57:16", "distance (en metres)": 42.5, "station": "CONCORDE-ROYALE", "marker-color": "#818181"}}, {"type": "Feature", "geometry": {"type": "Point", "coordinates": [2.319876, 48.861988]}, "properties": {"numparc": 1388, "etat de la localisation": "autre", "ID BDGEO": "13", "horodatage": "2021-06-13 19:38:07", "distance (en metres)": 58.05, "station": "ASSEMBLEE NATIONALE", "marker-color": "#818181"}}, {"type": "Feature", "geometry": {"type": "Point", "coordinates": [2.327924, 48.823708]}, "properties": {"numparc": 1388, "etat de la localisation": "autre", "ID BDGEO": "131", "horodatage": "2021-06-14 01:20:12", "distance (en metres)": 133.59, "station": "MONTROUGE SORTIE#", "marker-color": "#818181"}}, {"type": "Feature", "geometry": {"type": "Point", "coordinates": [2.328681, 48.823124]}, "properties": {"numparc": 1388, "etat de la localisation": "autre", "ID BDGEO": "131", "horodatage": "2021-06-14 01:24:16", "distance (en metres)": 77.44, "station": "MONTROUGE SORTIE#", "marker-color": "#818181"}}, {"type": "Feature", "geometry": {"type": "Point", "coordinates": [2.309453, 48.887731]}, "properties": {"station": "PEREIRE SAUSSURE", "ID BDGEO": "138", "marker-color": "#56B3FF"}}, {"type": "Feature", "geometry": {"type": "Point", "coordinates": [2.325401, 48.875349]}, "properties": {"station": "GARE SAINT-LAZARE", "ID BDGEO": "38", "marker-color": "#56B3FF"}}, {"type": "Feature", "geometry": {"type": "Point", "coordinates": [2.327381, 48.849735]}, "properties": {"station": "RUE DU CHERCHE MIDI", "ID BDGEO": "7", "marker-color": "#56B3FF"}}, {"type": "Feature", "geometry": {"type": "Point", "coordinates": [2.326237, 48.853573]}, "properties": {"station": "CHARLOTTE PERRIAND", "ID BDGEO": "9", "marker-color": "#56B3FF"}}, {"type": "Feature", "geometry": {"type": "Point", "coordinates": [2.279132, 48.897848]}, "properties": {"station": "PONT DE LEVALLOIS", "ID BDGEO": "109", "marker-color": "#56B3FF"}}, {"type": "Feature", "geometry": {"type": "Point", "coordinates": [2.322188, 48.866981]}, "properties": {"station": "CONCORDE-ROYALE", "ID BDGEO": "42", "marker-color": "#56B3FF"}}, {"type": "Feature", "geometry": {"type": "Point", "coordinates": [2.320187, 48.861508]}, "properties": {"station": "ASSEMBLEE NATIONALE", "ID BDGEO": "13", "marker-color": "#56B3FF"}}, {"type": "Feature", "geometry": {"type": "Point", "coordinates": [2.329673, 48.823366]}, "properties": {"station": "MONTROUGE SORTIE#", "ID BDGEO": "131", "marker-color": "#56B3FF"}}]}