{"type": "FeatureCollection", "features": [{"type": "Feature", "geometry": {"type": "Point", "coordinates": [2.427829, 48.87862]}, "properties": {"numparc": 4945, "etat de la localisation": "autre", "ID BDGEO": "17276", "horodatage": "2021-05-19 00:52:21", "distance (en metres)": 85.49, "station": "FLOREAL", "marker-color": "#818181"}}, {"type": "Feature", "geometry": {"type": "Point", "coordinates": [2.35327, 48.860832]}, "properties": {"numparc": 4945, "etat de la localisation": "autre", "ID BDGEO": "17237", "horodatage": "2021-05-19 01:25:28", "distance (en metres)": 121.1, "station": "CENTRE GEORGES POMPIDOU", "marker-color": "#818181"}}, {"type": "Feature", "geometry": {"type": "Point", "coordinates": [2.320006, 48.842068]}, "properties": {"numparc": 4945, "etat de la localisation": "autre", "ID BDGEO": "17255", "horodatage": "2021-05-19 01:43:53", "distance (en metres)": 50.19, "station": "GARE MONTPARNASSE", "marker-color": "#818181"}}, {"type": "Feature", "geometry": {"type": "Point", "coordinates": [2.230046, 48.829273]}, "properties": {"numparc": 4945, "etat de la localisation": "Delocalise", "ID BDGEO": "22551", "horodatage": "2021-05-19 02:08:35", "distance (en metres)": 111.63, "station": "PONT DE SEVRES", "marker-color": "#FF565E"}}, {"type": "Feature", "geometry": {"type": "Point", "coordinates": [2.230046, 48.829273]}, "properties": {"numparc": 4945, "etat de la localisation": "autre", "ID BDGEO": "22551", "horodatage": "2021-05-19 02:14:13", "distance (en metres)": 111.63, "station": "PONT DE SEVRES", "marker-color": "#818181"}}, {"type": "Feature", "geometry": {"type": "Point", "coordinates": [2.427048, 48.878048]}, "properties": {"station": "FLOREAL", "ID BDGEO": "17276", "marker-color": "#56B3FF"}}, {"type": "Feature", "geometry": {"type": "Point", "coordinates": [2.352701, 48.859809]}, "properties": {"station": "CENTRE GEORGES POMPIDOU", "ID BDGEO": "17237", "marker-color": "#56B3FF"}}, {"type": "Feature", "geometry": {"type": "Point", "coordinates": [2.319404, 48.841852]}, "properties": {"station": "GARE MONTPARNASSE", "ID BDGEO": "17255", "marker-color": "#56B3FF"}}, {"type": "Feature", "geometry": {"type": "Point", "coordinates": [2.231345, 48.829799]}, "properties": {"station": "PONT DE SEVRES", "ID BDGEO": "22551", "marker-color": "#56B3FF"}}]}