{"type": "FeatureCollection", "features": [{"type": "Feature", "geometry": {"type": "Point", "coordinates": [2.42756, 48.879219]}, "properties": {"numparc": 4941, "etat de la localisation": "autre", "ID BDGEO": "327", "horodatage": "2021-06-20 06:06:22", "distance (en metres)": 43.9, "station": "CENTRE BUS LES LILAS SORTIE", "marker-color": "#818181"}}, {"type": "Feature", "geometry": {"type": "Point", "coordinates": [2.42756, 48.879219]}, "properties": {"numparc": 4941, "etat de la localisation": "autre", "ID BDGEO": "327", "horodatage": "2021-06-20 06:08:02", "distance (en metres)": 43.9, "station": "CENTRE BUS LES LILAS SORTIE", "marker-color": "#818181"}}, {"type": "Feature", "geometry": {"type": "Point", "coordinates": [2.427023, 48.879396]}, "properties": {"station": "CENTRE BUS LES LILAS SORTIE", "ID BDGEO": "327", "marker-color": "#56B3FF"}}]}